{
"meta":{"test_sets":[],"test_metrics":[],"learn_metrics":[{"best_value":"Min","name":"Logloss"}],"launch_mode":"Train","parameters":"","iteration_count":1000,"learn_sets":["learn"],"name":"experiment"},
"iterations":[
{"learn":[0.6007710825],"iteration":0,"passed_time":0.07488961151,"remaining_time":74.8147219},
{"learn":[0.5012674083],"iteration":1,"passed_time":0.09405665623,"remaining_time":46.93427146},
{"learn":[0.4182272889],"iteration":2,"passed_time":0.1132977674,"remaining_time":37.65262469},
{"learn":[0.3493286738],"iteration":3,"passed_time":0.137528853,"remaining_time":34.2446844},
{"learn":[0.2948755825],"iteration":4,"passed_time":0.1516424963,"remaining_time":30.17685675},
{"learn":[0.2479080773],"iteration":5,"passed_time":0.1695018234,"remaining_time":28.08080208},
{"learn":[0.2098393272],"iteration":6,"passed_time":0.181447134,"remaining_time":25.739572},
{"learn":[0.171640893],"iteration":7,"passed_time":0.1933994008,"remaining_time":23.9815257},
{"learn":[0.1427481015],"iteration":8,"passed_time":0.2100217964,"remaining_time":23.12573336},
{"learn":[0.119131256],"iteration":9,"passed_time":0.2218534886,"remaining_time":21.96349537},
{"learn":[0.09719072691],"iteration":10,"passed_time":0.2328582003,"remaining_time":20.9360691},
{"learn":[0.08025283871],"iteration":11,"passed_time":0.2533555336,"remaining_time":20.8596056},
{"learn":[0.06757631235],"iteration":12,"passed_time":0.2655388598,"remaining_time":20.16052728},
{"learn":[0.05710490386],"iteration":13,"passed_time":0.2812892903,"remaining_time":19.81080288},
{"learn":[0.04884964862],"iteration":14,"passed_time":0.2934576304,"remaining_time":19.27038439},
{"learn":[0.04201819512],"iteration":15,"passed_time":0.3060077242,"remaining_time":18.81947504},
{"learn":[0.03657706703],"iteration":16,"passed_time":0.3197255592,"remaining_time":18.48766028},
{"learn":[0.03216026089],"iteration":17,"passed_time":0.331560665,"remaining_time":18.08847628},
{"learn":[0.02865119745],"iteration":18,"passed_time":0.3428620375,"remaining_time":17.70250836},
{"learn":[0.02547465587],"iteration":19,"passed_time":0.3556267739,"remaining_time":17.42571192},
{"learn":[0.02293433705],"iteration":20,"passed_time":0.3678030023,"remaining_time":17.14662568},
{"learn":[0.02087478447],"iteration":21,"passed_time":0.3837964676,"remaining_time":17.06149751},
{"learn":[0.01909514535],"iteration":22,"passed_time":0.3982863366,"remaining_time":16.9185109},
{"learn":[0.01757646515],"iteration":23,"passed_time":0.4101366752,"remaining_time":16.67889146},
{"learn":[0.01628489686],"iteration":24,"passed_time":0.423004825,"remaining_time":16.49718817},
{"learn":[0.0151368458],"iteration":25,"passed_time":0.4370468455,"remaining_time":16.37244721},
{"learn":[0.01421198152],"iteration":26,"passed_time":0.456054581,"remaining_time":16.43485583},
{"learn":[0.01336382574],"iteration":27,"passed_time":0.4807148514,"remaining_time":16.6876727},
{"learn":[0.01262682233],"iteration":28,"passed_time":0.4956641354,"remaining_time":16.5962026},
{"learn":[0.01206285824],"iteration":29,"passed_time":0.5150692978,"remaining_time":16.6539073},
{"learn":[0.01185708736],"iteration":30,"passed_time":0.5277471897,"remaining_time":16.4963557},
{"learn":[0.0112547354],"iteration":31,"passed_time":0.5405314056,"remaining_time":16.35107502},
{"learn":[0.01083021424],"iteration":32,"passed_time":0.5518157258,"remaining_time":16.16987293},
{"learn":[0.01042643751],"iteration":33,"passed_time":0.5634990418,"remaining_time":16.01000219},
{"learn":[0.01003141285],"iteration":34,"passed_time":0.5795700721,"remaining_time":15.97957484},
{"learn":[0.009684404983],"iteration":35,"passed_time":0.5919782876,"remaining_time":15.85186303},
{"learn":[0.009333297019],"iteration":36,"passed_time":0.604609694,"remaining_time":15.73619285},
{"learn":[0.008982696197],"iteration":37,"passed_time":0.6162726228,"remaining_time":15.60142798},
{"learn":[0.008768810984],"iteration":38,"passed_time":0.6302599145,"remaining_time":15.53025071},
{"learn":[0.008533247454],"iteration":39,"passed_time":0.6446894502,"remaining_time":15.4725468},
{"learn":[0.0084708882],"iteration":40,"passed_time":0.6570014667,"remaining_time":15.36742455},
{"learn":[0.008294900162],"iteration":41,"passed_time":0.6692645913,"remaining_time":15.26560663},
{"learn":[0.008222607426],"iteration":42,"passed_time":0.6852693517,"remaining_time":15.2512272},
{"learn":[0.008159824623],"iteration":43,"passed_time":0.6964977588,"remaining_time":15.13299676},
{"learn":[0.008082738815],"iteration":44,"passed_time":0.7079646083,"remaining_time":15.02458224},
{"learn":[0.007911781754],"iteration":45,"passed_time":0.724866945,"remaining_time":15.03311012},
{"learn":[0.007765600707],"iteration":46,"passed_time":0.7373453844,"remaining_time":14.95085428},
{"learn":[0.007730382701],"iteration":47,"passed_time":0.7496518238,"remaining_time":14.86809451},
{"learn":[0.007600002557],"iteration":48,"passed_time":0.7635032645,"remaining_time":14.81819601},
{"learn":[0.00748634456],"iteration":49,"passed_time":0.7745867249,"remaining_time":14.71714777},
{"learn":[0.007415127751],"iteration":50,"passed_time":0.7867793931,"remaining_time":14.64026753},
{"learn":[0.007301497679],"iteration":51,"passed_time":0.8024229066,"remaining_time":14.62878684},
{"learn":[0.007192862039],"iteration":52,"passed_time":0.8164486415,"remaining_time":14.58824271},
{"learn":[0.007078422787],"iteration":53,"passed_time":0.8286990661,"remaining_time":14.51757994},
{"learn":[0.007034033989],"iteration":54,"passed_time":0.8409755353,"remaining_time":14.44948874},
{"learn":[0.00694244335],"iteration":55,"passed_time":0.8520829985,"remaining_time":14.36368483},
{"learn":[0.006909000826],"iteration":56,"passed_time":0.8644746724,"remaining_time":14.30174765},
{"learn":[0.006844914369],"iteration":57,"passed_time":0.8805129173,"remaining_time":14.30074428},
{"learn":[0.006760403674],"iteration":58,"passed_time":0.8926343081,"remaining_time":14.23676074},
{"learn":[0.006733699642],"iteration":59,"passed_time":0.904234568,"remaining_time":14.16634157},
{"learn":[0.006712047853],"iteration":60,"passed_time":0.9227200439,"remaining_time":14.20383805},
{"learn":[0.006626816115],"iteration":61,"passed_time":0.9346164778,"remaining_time":14.13984284},
{"learn":[0.006577624373],"iteration":62,"passed_time":0.9468656784,"remaining_time":14.08274826},
{"learn":[0.006489821934],"iteration":63,"passed_time":0.9678975035,"remaining_time":14.15550099},
{"learn":[0.006416279048],"iteration":64,"passed_time":0.9803831577,"remaining_time":14.10243465},
{"learn":[0.006401206096],"iteration":65,"passed_time":0.9948972053,"remaining_time":14.07930288},
{"learn":[0.006350185494],"iteration":66,"passed_time":1.007907515,"remaining_time":14.03548823},
{"learn":[0.00631291153],"iteration":67,"passed_time":1.020161894,"remaining_time":13.9822189},
{"learn":[0.006288309989],"iteration":68,"passed_time":1.033395801,"remaining_time":13.94335494},
{"learn":[0.00625816952],"iteration":69,"passed_time":1.04465674,"remaining_time":13.87901097},
{"learn":[0.006186776123],"iteration":70,"passed_time":1.057339697,"remaining_time":13.83476871},
{"learn":[0.006164471338],"iteration":71,"passed_time":1.075213787,"remaining_time":13.85831103},
{"learn":[0.006141014395],"iteration":72,"passed_time":1.087466123,"remaining_time":13.80933008},
{"learn":[0.006123034617],"iteration":73,"passed_time":1.100168335,"remaining_time":13.76697133},
{"learn":[0.006052513946],"iteration":74,"passed_time":1.112276501,"remaining_time":13.71807684},
{"learn":[0.006038601067],"iteration":75,"passed_time":1.123066714,"remaining_time":13.65412689},
{"learn":[0.006014619248],"iteration":76,"passed_time":1.135319208,"remaining_time":13.60908609},
{"learn":[0.005970601195],"iteration":77,"passed_time":1.147085174,"remaining_time":13.55913501},
{"learn":[0.005949164197],"iteration":78,"passed_time":1.160004089,"remaining_time":13.52359197},
{"learn":[0.005869508977],"iteration":79,"passed_time":1.174417657,"remaining_time":13.50580306},
{"learn":[0.005833036268],"iteration":80,"passed_time":1.186385847,"remaining_time":13.46035301},
{"learn":[0.005797752308],"iteration":81,"passed_time":1.199009098,"remaining_time":13.42305307},
{"learn":[0.005776166481],"iteration":82,"passed_time":1.210798274,"remaining_time":13.37713274},
{"learn":[0.00573231191],"iteration":83,"passed_time":1.222895874,"remaining_time":13.33538834},
{"learn":[0.00568842662],"iteration":84,"passed_time":1.234493756,"remaining_time":13.2889622},
{"learn":[0.00563889532],"iteration":85,"passed_time":1.246151667,"remaining_time":13.243984},
{"learn":[0.005613991919],"iteration":86,"passed_time":1.257978289,"remaining_time":13.20154227},
{"learn":[0.005596253255],"iteration":87,"passed_time":1.274268748,"remaining_time":13.20605793},
{"learn":[0.00557367013],"iteration":88,"passed_time":1.285956695,"remaining_time":13.16299494},
{"learn":[0.005513053419],"iteration":89,"passed_time":1.297894083,"remaining_time":13.12315129},
{"learn":[0.005469166229],"iteration":90,"passed_time":1.309836074,"remaining_time":13.08396694},
{"learn":[0.005423212256],"iteration":91,"passed_time":1.321421176,"remaining_time":13.04185248},
{"learn":[0.005382280551],"iteration":92,"passed_time":1.334954885,"remaining_time":13.01939872},
{"learn":[0.005347337374],"iteration":93,"passed_time":1.347532593,"remaining_time":12.98792052},
{"learn":[0.005318333058],"iteration":94,"passed_time":1.360818997,"remaining_time":12.9635915},
{"learn":[0.005288620606],"iteration":95,"passed_time":1.378872483,"remaining_time":12.98438255},
{"learn":[0.005265884575],"iteration":96,"passed_time":1.390783928,"remaining_time":12.94719471},
{"learn":[0.005212655072],"iteration":97,"passed_time":1.40259523,"remaining_time":12.90960099},
{"learn":[0.005170554802],"iteration":98,"passed_time":1.418519049,"remaining_time":12.90995619},
{"learn":[0.005141192698],"iteration":99,"passed_time":1.431999693,"remaining_time":12.88799723},
{"learn":[0.005132787164],"iteration":100,"passed_time":1.443922697,"remaining_time":12.85234163},
{"learn":[0.005114813043],"iteration":101,"passed_time":1.457354995,"remaining_time":12.83043908},
{"learn":[0.005077461473],"iteration":102,"passed_time":1.470170072,"remaining_time":12.80332577},
{"learn":[0.005044089042],"iteration":103,"passed_time":1.48461238,"remaining_time":12.79050666},
{"learn":[0.005011312332],"iteration":104,"passed_time":1.497091211,"remaining_time":12.76092032},
{"learn":[0.004989123887],"iteration":105,"passed_time":1.508420437,"remaining_time":12.72196104},
{"learn":[0.004950697235],"iteration":106,"passed_time":1.530319052,"remaining_time":12.77172817},
{"learn":[0.004934288624],"iteration":107,"passed_time":1.543223031,"remaining_time":12.74587911},
{"learn":[0.004924995642],"iteration":108,"passed_time":1.558376507,"remaining_time":12.73865566},
{"learn":[0.004914727719],"iteration":109,"passed_time":1.573641083,"remaining_time":12.73218694},
{"learn":[0.004900152052],"iteration":110,"passed_time":1.585555425,"remaining_time":12.69872768},
{"learn":[0.004858902633],"iteration":111,"passed_time":1.60488088,"remaining_time":12.72441269},
{"learn":[0.004826298549],"iteration":112,"passed_time":1.619107119,"remaining_time":12.70927447},
{"learn":[0.004816899733],"iteration":113,"passed_time":1.63169726,"remaining_time":12.6814366},
{"learn":[0.004795230357],"iteration":114,"passed_time":1.645726645,"remaining_time":12.66493983},
{"learn":[0.004779212296],"iteration":115,"passed_time":1.658177802,"remaining_time":12.63645843},
{"learn":[0.004762067462],"iteration":116,"passed_time":1.670705032,"remaining_time":12.60882515},
{"learn":[0.004743043132],"iteration":117,"passed_time":1.681548236,"remaining_time":12.56886055},
{"learn":[0.004727306664],"iteration":118,"passed_time":1.693862813,"remaining_time":12.54027847},
{"learn":[0.004697870854],"iteration":119,"passed_time":1.712186449,"remaining_time":12.55603396},
{"learn":[0.004690623571],"iteration":120,"passed_time":1.724724465,"remaining_time":12.52919673},
{"learn":[0.004675959583],"iteration":121,"passed_time":1.737024946,"remaining_time":12.50088444},
{"learn":[0.004652373223],"iteration":122,"passed_time":1.756965047,"remaining_time":12.52730363},
{"learn":[0.004641306501],"iteration":123,"passed_time":1.770018068,"remaining_time":12.50432119},
{"learn":[0.004626853207],"iteration":124,"passed_time":1.783101118,"remaining_time":12.48170783},
{"learn":[0.004598224669],"iteration":125,"passed_time":1.795081956,"remaining_time":12.45160023},
{"learn":[0.004568987783],"iteration":126,"passed_time":1.807908066,"remaining_time":12.42758852},
{"learn":[0.004560470154],"iteration":127,"passed_time":1.820983119,"remaining_time":12.4054475},
{"learn":[0.004538395664],"iteration":128,"passed_time":1.833549796,"remaining_time":12.38001451},
{"learn":[0.004497114926],"iteration":129,"passed_time":1.846883624,"remaining_time":12.35991349},
{"learn":[0.004479361064],"iteration":130,"passed_time":1.85802995,"remaining_time":12.32540478},
{"learn":[0.004430175034],"iteration":131,"passed_time":1.870556804,"remaining_time":12.30032808},
{"learn":[0.004398211542],"iteration":132,"passed_time":1.888056197,"remaining_time":12.30785506},
{"learn":[0.004380153803],"iteration":133,"passed_time":1.900007643,"remaining_time":12.27915387},
{"learn":[0.004345114609],"iteration":134,"passed_time":1.912549195,"remaining_time":12.25448188},
{"learn":[0.004333611121],"iteration":135,"passed_time":1.931008997,"remaining_time":12.26758657},
{"learn":[0.004310135515],"iteration":136,"passed_time":1.943184657,"remaining_time":12.24064495},
{"learn":[0.004302473223],"iteration":137,"passed_time":1.953953424,"remaining_time":12.20512936},
{"learn":[0.004296860181],"iteration":138,"passed_time":1.966670232,"remaining_time":12.18203647},
{"learn":[0.004277569842],"iteration":139,"passed_time":1.979212091,"remaining_time":12.15801713},
{"learn":[0.004262830585],"iteration":140,"passed_time":1.991889908,"remaining_time":12.13498887},
{"learn":[0.004243766522],"iteration":141,"passed_time":2.002771497,"remaining_time":12.10125313},
{"learn":[0.004222077861],"iteration":142,"passed_time":2.016632741,"remaining_time":12.08569412},
{"learn":[0.004199101388],"iteration":143,"passed_time":2.035692798,"remaining_time":12.10106274},
{"learn":[0.004191116681],"iteration":144,"passed_time":2.048365384,"remaining_time":12.07829244},
{"learn":[0.004174718674],"iteration":145,"passed_time":2.064194018,"remaining_time":12.07412118},
{"learn":[0.004164258175],"iteration":146,"passed_time":2.078932463,"remaining_time":12.06346524},
{"learn":[0.004151338537],"iteration":147,"passed_time":2.091174591,"remaining_time":12.03838346},
{"learn":[0.004140407762],"iteration":148,"passed_time":2.103805645,"remaining_time":12.01569533},
{"learn":[0.004121800766],"iteration":149,"passed_time":2.115924708,"remaining_time":11.99024001},
{"learn":[0.004112254131],"iteration":150,"passed_time":2.127545285,"remaining_time":11.96215859},
{"learn":[0.004099129772],"iteration":151,"passed_time":2.144401918,"remaining_time":11.96350544},
{"learn":[0.004076766241],"iteration":152,"passed_time":2.15642079,"remaining_time":11.93783274},
{"learn":[0.004059271152],"iteration":153,"passed_time":2.168784463,"remaining_time":11.91423153},
{"learn":[0.004059269007],"iteration":154,"passed_time":2.180282042,"remaining_time":11.88605371},
{"learn":[0.004045387227],"iteration":155,"passed_time":2.191794914,"remaining_time":11.85817248},
{"learn":[0.00400657115],"iteration":156,"passed_time":2.204135152,"remaining_time":11.83494225},
{"learn":[0.00398818802],"iteration":157,"passed_time":2.222013919,"remaining_time":11.84136532},
{"learn":[0.003975064561],"iteration":158,"passed_time":2.234479659,"remaining_time":11.81885153},
{"learn":[0.003954399007],"iteration":159,"passed_time":2.249055777,"remaining_time":11.80754283},
{"learn":[0.003944811312],"iteration":160,"passed_time":2.261537871,"remaining_time":11.7852812},
{"learn":[0.003929680413],"iteration":161,"passed_time":2.272610555,"remaining_time":11.75584966},
{"learn":[0.003923453749],"iteration":162,"passed_time":2.284924169,"remaining_time":11.73301552},
{"learn":[0.003903732198],"iteration":163,"passed_time":2.296934189,"remaining_time":11.70876209},
{"learn":[0.003887999937],"iteration":164,"passed_time":2.308749114,"remaining_time":11.68366976},
{"learn":[0.003864975092],"iteration":165,"passed_time":2.320700289,"remaining_time":11.65942193},
{"learn":[0.003830623099],"iteration":166,"passed_time":2.333675014,"remaining_time":11.64042687},
{"learn":[0.003819338595],"iteration":167,"passed_time":2.346514423,"remaining_time":11.62083333},
{"learn":[0.003803927592],"iteration":168,"passed_time":2.358705385,"remaining_time":11.59813121},
{"learn":[0.003803925109],"iteration":169,"passed_time":2.367409272,"remaining_time":11.55852762},
{"learn":[0.003780324934],"iteration":170,"passed_time":2.383765838,"remaining_time":11.55638526},
{"learn":[0.003762498294],"iteration":171,"passed_time":2.396988068,"remaining_time":11.53898907},
{"learn":[0.003762495392],"iteration":172,"passed_time":2.408835453,"remaining_time":11.5150689},
{"learn":[0.003733748662],"iteration":173,"passed_time":2.425229256,"remaining_time":11.51286992},
{"learn":[0.003714975044],"iteration":174,"passed_time":2.437341357,"remaining_time":11.49032354},
{"learn":[0.003706335778],"iteration":175,"passed_time":2.448452219,"remaining_time":11.46320812},
{"learn":[0.00368865304],"iteration":176,"passed_time":2.461020861,"remaining_time":11.4430518},
{"learn":[0.003682005174],"iteration":177,"passed_time":2.473156251,"remaining_time":11.42097999},
{"learn":[0.003660567422],"iteration":178,"passed_time":2.487498384,"remaining_time":11.40914063},
{"learn":[0.003648736416],"iteration":179,"passed_time":2.498596019,"remaining_time":11.38249297},
{"learn":[0.003635059677],"iteration":180,"passed_time":2.510363639,"remaining_time":11.35904873},
{"learn":[0.003620243419],"iteration":181,"passed_time":2.52267603,"remaining_time":11.33818128},
{"learn":[0.003592424916],"iteration":182,"passed_time":2.535338074,"remaining_time":11.31896834},
{"learn":[0.003592421812],"iteration":183,"passed_time":2.543538295,"remaining_time":11.28003939},
{"learn":[0.003592421812],"iteration":184,"passed_time":2.553078934,"remaining_time":11.24734774},
{"learn":[0.003580301875],"iteration":185,"passed_time":2.564748996,"remaining_time":11.2242241},
{"learn":[0.003566330285],"iteration":186,"passed_time":2.576026685,"remaining_time":11.19951708},
{"learn":[0.003566318009],"iteration":187,"passed_time":2.58218444,"remaining_time":11.15283918},
{"learn":[0.003542477778],"iteration":188,"passed_time":2.59452166,"remaining_time":11.13310617},
{"learn":[0.003542475276],"iteration":189,"passed_time":2.604243698,"remaining_time":11.10230208},
{"learn":[0.003542249856],"iteration":190,"passed_time":2.61446767,"remaining_time":11.07384474},
{"learn":[0.003521127714],"iteration":191,"passed_time":2.626295855,"remaining_time":11.05232839},
{"learn":[0.003494671561],"iteration":192,"passed_time":2.638184573,"remaining_time":11.03116555},
{"learn":[0.003472687572],"iteration":193,"passed_time":2.651187548,"remaining_time":11.01472765},
{"learn":[0.003472685066],"iteration":194,"passed_time":2.660696088,"remaining_time":10.98389924},
{"learn":[0.003450921547],"iteration":195,"passed_time":2.672287306,"remaining_time":10.9618316},
{"learn":[0.003415753552],"iteration":196,"passed_time":2.685254131,"remaining_time":10.9454775},
{"learn":[0.003398948229],"iteration":197,"passed_time":2.697235898,"remaining_time":10.92516763},
{"learn":[0.003398942927],"iteration":198,"passed_time":2.707919732,"remaining_time":10.89971711},
{"learn":[0.003386793169],"iteration":199,"passed_time":2.719135488,"remaining_time":10.87654195},
{"learn":[0.003379928678],"iteration":200,"passed_time":2.731703648,"remaining_time":10.85886176},
{"learn":[0.003368533904],"iteration":201,"passed_time":2.744231984,"remaining_time":10.84107487},
{"learn":[0.003368533904],"iteration":202,"passed_time":2.752032801,"remaining_time":10.80477903},
{"learn":[0.003363471262],"iteration":203,"passed_time":2.764379969,"remaining_time":10.78650223},
{"learn":[0.003356139264],"iteration":204,"passed_time":2.779686729,"remaining_time":10.77976073},
{"learn":[0.003356136694],"iteration":205,"passed_time":2.788576558,"remaining_time":10.74820285},
{"learn":[0.003328817951],"iteration":206,"passed_time":2.800067871,"remaining_time":10.72683006},
{"learn":[0.003318099046],"iteration":207,"passed_time":2.812125396,"remaining_time":10.70770824},
{"learn":[0.00331298239],"iteration":208,"passed_time":2.823938543,"remaining_time":10.68772913},
{"learn":[0.00331298239],"iteration":209,"passed_time":2.831902052,"remaining_time":10.65334582},
{"learn":[0.00329720897],"iteration":210,"passed_time":2.844428482,"remaining_time":10.63627522},
{"learn":[0.003292752155],"iteration":211,"passed_time":2.855374458,"remaining_time":10.61337299},
{"learn":[0.003280804746],"iteration":212,"passed_time":2.866760055,"remaining_time":10.59220734},
{"learn":[0.003273931271],"iteration":213,"passed_time":2.877858018,"remaining_time":10.57007665},
{"learn":[0.00327392859],"iteration":214,"passed_time":2.887250176,"remaining_time":10.54182041},
{"learn":[0.003266163345],"iteration":215,"passed_time":2.899317883,"remaining_time":10.52345009},
{"learn":[0.003259050796],"iteration":216,"passed_time":2.910025552,"remaining_time":10.50023045},
{"learn":[0.003259044102],"iteration":217,"passed_time":2.919359578,"remaining_time":10.47219812},
{"learn":[0.003238157027],"iteration":218,"passed_time":2.93046746,"remaining_time":10.45066249},
{"learn":[0.003238152859],"iteration":219,"passed_time":2.938488931,"remaining_time":10.41827894},
{"learn":[0.003238149179],"iteration":220,"passed_time":2.943201991,"remaining_time":10.37445408},
{"learn":[0.003223232785],"iteration":221,"passed_time":2.956658092,"remaining_time":10.3616216},
{"learn":[0.003223227718],"iteration":222,"passed_time":2.968623689,"remaining_time":10.34359016},
{"learn":[0.003223225631],"iteration":223,"passed_time":2.977896095,"remaining_time":10.3162829},
{"learn":[0.003200148292],"iteration":224,"passed_time":2.989677629,"remaining_time":10.2977785},
{"learn":[0.003200145463],"iteration":225,"passed_time":2.99904474,"remaining_time":10.27106473},
{"learn":[0.003184230958],"iteration":226,"passed_time":3.011607981,"remaining_time":10.25538753},
{"learn":[0.003166172935],"iteration":227,"passed_time":3.022860965,"remaining_time":10.23530116},
{"learn":[0.003152156039],"iteration":228,"passed_time":3.034570366,"remaining_time":10.21682861},
{"learn":[0.003145878944],"iteration":229,"passed_time":3.046314572,"remaining_time":10.19853139},
{"learn":[0.003135861917],"iteration":230,"passed_time":3.058022525,"remaining_time":10.18017022},
{"learn":[0.003135856734],"iteration":231,"passed_time":3.066301679,"remaining_time":10.1505159},
{"learn":[0.00312599304],"iteration":232,"passed_time":3.076994224,"remaining_time":10.12898957},
{"learn":[0.00311040019],"iteration":233,"passed_time":3.088718787,"remaining_time":10.11093415},
{"learn":[0.003095376631],"iteration":234,"passed_time":3.099889429,"remaining_time":10.09112942},
{"learn":[0.003089897271],"iteration":235,"passed_time":3.111573301,"remaining_time":10.07305933},
{"learn":[0.003079998833],"iteration":236,"passed_time":3.122775821,"remaining_time":10.05349347},
{"learn":[0.003079993945],"iteration":237,"passed_time":3.131825194,"remaining_time":10.02710419},
{"learn":[0.003079991797],"iteration":238,"passed_time":3.142126013,"remaining_time":10.00484475},
{"learn":[0.003067203504],"iteration":239,"passed_time":3.15377092,"remaining_time":9.986941247},
{"learn":[0.003067203504],"iteration":240,"passed_time":3.160218803,"remaining_time":9.952722288},
{"learn":[0.003043407095],"iteration":241,"passed_time":3.172098689,"remaining_time":9.935747134},
{"learn":[0.003036679165],"iteration":242,"passed_time":3.183332913,"remaining_time":9.916802532},
{"learn":[0.00303667196],"iteration":243,"passed_time":3.191357271,"remaining_time":9.887975805},
{"learn":[0.003026346461],"iteration":244,"passed_time":3.202872194,"remaining_time":9.870075536},
{"learn":[0.003026343292],"iteration":245,"passed_time":3.210665047,"remaining_time":9.840818884},
{"learn":[0.003020939934],"iteration":246,"passed_time":3.222393469,"remaining_time":9.823733935},
{"learn":[0.003009101803],"iteration":247,"passed_time":3.232890178,"remaining_time":9.802957315},
{"learn":[0.002997255906],"iteration":248,"passed_time":3.244141473,"remaining_time":9.784539141},
{"learn":[0.002989192012],"iteration":249,"passed_time":3.255590668,"remaining_time":9.766772004},
{"learn":[0.002975437987],"iteration":250,"passed_time":3.267008465,"remaining_time":9.748961515},
{"learn":[0.002968955246],"iteration":251,"passed_time":3.278565695,"remaining_time":9.731615636},
{"learn":[0.002968951319],"iteration":252,"passed_time":3.286898213,"remaining_time":9.70479433},
{"learn":[0.002956427415],"iteration":253,"passed_time":3.298475241,"remaining_time":9.687647755},
{"learn":[0.002951521674],"iteration":254,"passed_time":3.311198538,"remaining_time":9.673893769},
{"learn":[0.002939398691],"iteration":255,"passed_time":3.323613576,"remaining_time":9.659251956},
{"learn":[0.002933474197],"iteration":256,"passed_time":3.335268676,"remaining_time":9.642430453},
{"learn":[0.002922346623],"iteration":257,"passed_time":3.347521282,"remaining_time":9.627367408},
{"learn":[0.002910862338],"iteration":258,"passed_time":3.360515345,"remaining_time":9.614447376},
{"learn":[0.002901934729],"iteration":259,"passed_time":3.372064223,"remaining_time":9.597413557},
{"learn":[0.002897712337],"iteration":260,"passed_time":3.385038893,"remaining_time":9.58445878},
{"learn":[0.002891574189],"iteration":261,"passed_time":3.39756934,"remaining_time":9.57025257},
{"learn":[0.002871072259],"iteration":262,"passed_time":3.410592264,"remaining_time":9.557439159},
{"learn":[0.002871070648],"iteration":263,"passed_time":3.418609532,"remaining_time":9.530668998},
{"learn":[0.002859671413],"iteration":264,"passed_time":3.430357089,"remaining_time":9.514386644},
{"learn":[0.002847531672],"iteration":265,"passed_time":3.442830148,"remaining_time":9.500140334},
{"learn":[0.002837020221],"iteration":266,"passed_time":3.45319886,"remaining_time":9.480130204},
{"learn":[0.002827635637],"iteration":267,"passed_time":3.46519686,"remaining_time":9.46464217},
{"learn":[0.002820967735],"iteration":268,"passed_time":3.481290797,"remaining_time":9.460310679},
{"learn":[0.002811526797],"iteration":269,"passed_time":3.496509036,"remaining_time":9.45352443},
{"learn":[0.002807006523],"iteration":270,"passed_time":3.511443526,"remaining_time":9.445912658},
{"learn":[0.002807004526],"iteration":271,"passed_time":3.521249834,"remaining_time":9.424521615},
{"learn":[0.002807004526],"iteration":272,"passed_time":3.529120931,"remaining_time":9.398061967},
{"learn":[0.0027977885],"iteration":273,"passed_time":3.541607278,"remaining_time":9.38396673},
{"learn":[0.002788943466],"iteration":274,"passed_time":3.554133839,"remaining_time":9.369989212},
{"learn":[0.002788937207],"iteration":275,"passed_time":3.562175987,"remaining_time":9.344258749},
{"learn":[0.002788929824],"iteration":276,"passed_time":3.571675993,"remaining_time":9.322461166},
{"learn":[0.002780823164],"iteration":277,"passed_time":3.58374146,"remaining_time":9.307414871},
{"learn":[0.002780818828],"iteration":278,"passed_time":3.592029189,"remaining_time":9.282627401},
{"learn":[0.002780817579],"iteration":279,"passed_time":3.601466739,"remaining_time":9.260914472},
{"learn":[0.002775595364],"iteration":280,"passed_time":3.624028758,"remaining_time":9.272870736},
{"learn":[0.002767575721],"iteration":281,"passed_time":3.640348254,"remaining_time":9.268688107},
{"learn":[0.002759087552],"iteration":282,"passed_time":3.652263095,"remaining_time":9.253260209},
{"learn":[0.002747859118],"iteration":283,"passed_time":3.665139253,"remaining_time":9.240280653},
{"learn":[0.002731438015],"iteration":284,"passed_time":3.67828383,"remaining_time":9.227975223},
{"learn":[0.002723331564],"iteration":285,"passed_time":3.69133133,"remaining_time":9.215421572},
{"learn":[0.002715388893],"iteration":286,"passed_time":3.703479206,"remaining_time":9.200629527},
{"learn":[0.002708461151],"iteration":287,"passed_time":3.715105618,"remaining_time":9.184566666},
{"learn":[0.002692787876],"iteration":288,"passed_time":3.728249412,"remaining_time":9.172267585},
{"learn":[0.002692785371],"iteration":289,"passed_time":3.736432157,"remaining_time":9.147816661},
{"learn":[0.002674875082],"iteration":290,"passed_time":3.748815401,"remaining_time":9.133711749},
{"learn":[0.002664265454],"iteration":291,"passed_time":3.7604224,"remaining_time":9.117736505},
{"learn":[0.002664262708],"iteration":292,"passed_time":3.768603551,"remaining_time":9.093524609},
{"learn":[0.002664238861],"iteration":293,"passed_time":3.77790196,"remaining_time":9.072104707},
{"learn":[0.002658237245],"iteration":294,"passed_time":3.79044554,"remaining_time":9.058522392},
{"learn":[0.002651066759],"iteration":295,"passed_time":3.801264895,"remaining_time":9.040846236},
{"learn":[0.002651066759],"iteration":296,"passed_time":3.810819444,"remaining_time":9.020222455},
{"learn":[0.002635032085],"iteration":297,"passed_time":3.823590333,"remaining_time":9.007249711},
{"learn":[0.002635029506],"iteration":298,"passed_time":3.831578186,"remaining_time":8.983064577},
{"learn":[0.002620666752],"iteration":299,"passed_time":3.843895122,"remaining_time":8.969088619},
{"learn":[0.002620660813],"iteration":300,"passed_time":3.855855414,"remaining_time":8.954295464},
{"learn":[0.002620649414],"iteration":301,"passed_time":3.865387084,"remaining_time":8.933907896},
{"learn":[0.002620649414],"iteration":302,"passed_time":3.874528056,"remaining_time":8.912693251},
{"learn":[0.00262064431],"iteration":303,"passed_time":3.882735391,"remaining_time":8.889420501},
{"learn":[0.002613646533],"iteration":304,"passed_time":3.894076371,"remaining_time":8.87338714},
{"learn":[0.002608790745],"iteration":305,"passed_time":3.906194547,"remaining_time":8.85914711},
{"learn":[0.002602758774],"iteration":306,"passed_time":3.918322876,"remaining_time":8.844943821},
{"learn":[0.002602755133],"iteration":307,"passed_time":3.926206637,"remaining_time":8.82121751},
{"learn":[0.00260275381],"iteration":308,"passed_time":3.935054932,"remaining_time":8.799750673},
{"learn":[0.002602751502],"iteration":309,"passed_time":3.943901428,"remaining_time":8.778361243},
{"learn":[0.002602749005],"iteration":310,"passed_time":3.95394251,"remaining_time":8.759699001},
{"learn":[0.002592654965],"iteration":311,"passed_time":3.966196933,"remaining_time":8.745972724},
{"learn":[0.002585117487],"iteration":312,"passed_time":3.976418963,"remaining_time":8.727794975},
{"learn":[0.002585115479],"iteration":313,"passed_time":3.985565167,"remaining_time":8.707317531},
{"learn":[0.002585115479],"iteration":314,"passed_time":3.993313038,"remaining_time":8.68387121},
{"learn":[0.002585113057],"iteration":315,"passed_time":4.002675898,"remaining_time":8.664019982},
{"learn":[0.002585113057],"iteration":316,"passed_time":4.01108096,"remaining_time":8.642171281},
{"learn":[0.002578161956],"iteration":317,"passed_time":4.021173365,"remaining_time":8.624025896},
{"learn":[0.002578161956],"iteration":318,"passed_time":4.033011254,"remaining_time":8.609657254},
{"learn":[0.002578161403],"iteration":319,"passed_time":4.041201531,"remaining_time":8.587553253},
{"learn":[0.00257168884],"iteration":320,"passed_time":4.052927807,"remaining_time":8.573015517},
{"learn":[0.002571679125],"iteration":321,"passed_time":4.062537188,"remaining_time":8.554037929},
{"learn":[0.002571675896],"iteration":322,"passed_time":4.070762859,"remaining_time":8.532218128},
{"learn":[0.002558972456],"iteration":323,"passed_time":4.083252004,"remaining_time":8.519377637},
{"learn":[0.002545221009],"iteration":324,"passed_time":4.095413893,"remaining_time":8.505859623},
{"learn":[0.002545218665],"iteration":325,"passed_time":4.103433957,"remaining_time":8.483786769},
{"learn":[0.002532734311],"iteration":326,"passed_time":4.115842314,"remaining_time":8.470831428},
{"learn":[0.002532732161],"iteration":327,"passed_time":4.125113791,"remaining_time":8.451452645},
{"learn":[0.002519627066],"iteration":328,"passed_time":4.136493632,"remaining_time":8.43643534},
{"learn":[0.002514626266],"iteration":329,"passed_time":4.147684181,"remaining_time":8.421055761},
{"learn":[0.002514594048],"iteration":330,"passed_time":4.157566392,"remaining_time":8.403057149},
{"learn":[0.002514568572],"iteration":331,"passed_time":4.167365644,"remaining_time":8.384940512},
{"learn":[0.002514562211],"iteration":332,"passed_time":4.176904331,"remaining_time":8.366351918},
{"learn":[0.002514562211],"iteration":333,"passed_time":4.18482603,"remaining_time":8.344593222},
{"learn":[0.002514560121],"iteration":334,"passed_time":4.19336748,"remaining_time":8.324147386},
{"learn":[0.002514555368],"iteration":335,"passed_time":4.205411942,"remaining_time":8.310695028},
{"learn":[0.00250937281],"iteration":336,"passed_time":4.215865556,"remaining_time":8.294121258},
{"learn":[0.00250937281],"iteration":337,"passed_time":4.224787515,"remaining_time":8.274583832},
{"learn":[0.002509370508],"iteration":338,"passed_time":4.23382428,"remaining_time":8.255332888},
{"learn":[0.002498409145],"iteration":339,"passed_time":4.244747797,"remaining_time":8.239804548},
{"learn":[0.002498402628],"iteration":340,"passed_time":4.254319045,"remaining_time":8.221689885},
{"learn":[0.002498401516],"iteration":341,"passed_time":4.262407921,"remaining_time":8.200773134},
{"learn":[0.002498399433],"iteration":342,"passed_time":4.271893208,"remaining_time":8.18260594},
{"learn":[0.00249839119],"iteration":343,"passed_time":4.280816599,"remaining_time":8.1634177},
{"learn":[0.002498383647],"iteration":344,"passed_time":4.289341563,"remaining_time":8.143532532},
{"learn":[0.002498381419],"iteration":345,"passed_time":4.298791848,"remaining_time":8.125462049},
{"learn":[0.002498330774],"iteration":346,"passed_time":4.30727024,"remaining_time":8.105612296},
{"learn":[0.002498330774],"iteration":347,"passed_time":4.318224906,"remaining_time":8.090467352},
{"learn":[0.002498327915],"iteration":348,"passed_time":4.3264671,"remaining_time":8.070286769},
{"learn":[0.002498297746],"iteration":349,"passed_time":4.335869976,"remaining_time":8.052329955},
{"learn":[0.002498289508],"iteration":350,"passed_time":4.345102376,"remaining_time":8.034106673},
{"learn":[0.002498259334],"iteration":351,"passed_time":4.353712918,"remaining_time":8.014789689},
{"learn":[0.002498259334],"iteration":352,"passed_time":4.363033788,"remaining_time":7.996835301},
{"learn":[0.002498259334],"iteration":353,"passed_time":4.372351413,"remaining_time":7.978923764},
{"learn":[0.002498259334],"iteration":354,"passed_time":4.382887074,"remaining_time":7.963273698},
{"learn":[0.002498244272],"iteration":355,"passed_time":4.396866754,"remaining_time":7.953882555},
{"learn":[0.00249821897],"iteration":356,"passed_time":4.407625442,"remaining_time":7.938664312},
{"learn":[0.00249818761],"iteration":357,"passed_time":4.416716082,"remaining_time":7.920479678},
{"learn":[0.002498186175],"iteration":358,"passed_time":4.426228746,"remaining_time":7.903099237},
{"learn":[0.002498186175],"iteration":359,"passed_time":4.434383397,"remaining_time":7.883348261},
{"learn":[0.002498186175],"iteration":360,"passed_time":4.443657526,"remaining_time":7.865643099},
{"learn":[0.002498177938],"iteration":361,"passed_time":4.452010799,"remaining_time":7.846361574},
{"learn":[0.002498171025],"iteration":362,"passed_time":4.460823205,"remaining_time":7.827945955},
{"learn":[0.002498157219],"iteration":363,"passed_time":4.470232312,"remaining_time":7.810625688},
{"learn":[0.002498151721],"iteration":364,"passed_time":4.47837918,"remaining_time":7.79115282},
{"learn":[0.002489753882],"iteration":365,"passed_time":4.490569046,"remaining_time":7.778745287},
{"learn":[0.002489723704],"iteration":366,"passed_time":4.498884082,"remaining_time":7.759655652},
{"learn":[0.00248972167],"iteration":367,"passed_time":4.507358937,"remaining_time":7.740899044},
{"learn":[0.002489706075],"iteration":368,"passed_time":4.516508434,"remaining_time":7.723351821},
{"learn":[0.002489704841],"iteration":369,"passed_time":4.525551637,"remaining_time":7.705669003},
{"learn":[0.002489704841],"iteration":370,"passed_time":4.5352548,"remaining_time":7.689151669},
{"learn":[0.002489702114],"iteration":371,"passed_time":4.54328507,"remaining_time":7.669846839},
{"learn":[0.002489700826],"iteration":372,"passed_time":4.553036764,"remaining_time":7.653496116},
{"learn":[0.002489700826],"iteration":373,"passed_time":4.563621295,"remaining_time":7.638574682},
{"learn":[0.00248970003],"iteration":374,"passed_time":4.572616096,"remaining_time":7.621026827},
{"learn":[0.002489697304],"iteration":375,"passed_time":4.581951323,"remaining_time":7.604089429},
{"learn":[0.0024802053],"iteration":376,"passed_time":4.592371408,"remaining_time":7.588985112},
{"learn":[0.002480200991],"iteration":377,"passed_time":4.601743635,"remaining_time":7.572181325},
{"learn":[0.00248019301],"iteration":378,"passed_time":4.610552977,"remaining_time":7.554494456},
{"learn":[0.00248019301],"iteration":379,"passed_time":4.618569402,"remaining_time":7.535560603},
{"learn":[0.00248019301],"iteration":380,"passed_time":4.627833125,"remaining_time":7.518710511},
{"learn":[0.00248019301],"iteration":381,"passed_time":4.635739286,"remaining_time":7.499703871},
{"learn":[0.002480185295],"iteration":382,"passed_time":4.645359329,"remaining_time":7.483516204},
{"learn":[0.002480170279],"iteration":383,"passed_time":4.653621058,"remaining_time":7.46518378},
{"learn":[0.002480162769],"iteration":384,"passed_time":4.663063646,"remaining_time":7.448789979},
{"learn":[0.00248014288],"iteration":385,"passed_time":4.671515081,"remaining_time":7.430855595},
{"learn":[0.00248014288],"iteration":386,"passed_time":4.680022447,"remaining_time":7.413058811},
{"learn":[0.00248014288],"iteration":387,"passed_time":4.688752166,"remaining_time":7.395660633},
{"learn":[0.002480112848],"iteration":388,"passed_time":4.697027022,"remaining_time":7.377592572},
{"learn":[0.002480062917],"iteration":389,"passed_time":4.706492548,"remaining_time":7.361437062},
{"learn":[0.002480062917],"iteration":390,"passed_time":4.714390025,"remaining_time":7.342873466},
{"learn":[0.002480054304],"iteration":391,"passed_time":4.723604924,"remaining_time":7.326407637},
{"learn":[0.002480054304],"iteration":392,"passed_time":4.732537826,"remaining_time":7.309543157},
{"learn":[0.002480054304],"iteration":393,"passed_time":4.743971262,"remaining_time":7.296564936},
{"learn":[0.002480054304],"iteration":394,"passed_time":4.753210997,"remaining_time":7.280234564},
{"learn":[0.002480039298],"iteration":395,"passed_time":4.761252657,"remaining_time":7.262112638},
{"learn":[0.002480039298],"iteration":396,"passed_time":4.770488933,"remaining_time":7.245855986},
{"learn":[0.002480039298],"iteration":397,"passed_time":4.778632615,"remaining_time":7.227981996},
{"learn":[0.002480039298],"iteration":398,"passed_time":4.787788113,"remaining_time":7.211680842},
{"learn":[0.002480035549],"iteration":399,"passed_time":4.795689739,"remaining_time":7.193534608},
{"learn":[0.002479975536],"iteration":400,"passed_time":4.805362611,"remaining_time":7.178085296},
{"learn":[0.002479965553],"iteration":401,"passed_time":4.814334437,"remaining_time":7.161621874},
{"learn":[0.002479958055],"iteration":402,"passed_time":4.822699598,"remaining_time":7.144296923},
{"learn":[0.002470723788],"iteration":403,"passed_time":4.834316391,"remaining_time":7.13181329},
{"learn":[0.002470722437],"iteration":404,"passed_time":4.842531635,"remaining_time":7.114336599},
{"learn":[0.002470721087],"iteration":405,"passed_time":4.851870254,"remaining_time":7.09854909},
{"learn":[0.002470706098],"iteration":406,"passed_time":4.860186569,"remaining_time":7.081303772},
{"learn":[0.002470691124],"iteration":407,"passed_time":4.86943659,"remaining_time":7.065457013},
{"learn":[0.002470684247],"iteration":408,"passed_time":4.878978456,"remaining_time":7.050064224},
{"learn":[0.002470669271],"iteration":409,"passed_time":4.887231297,"remaining_time":7.032845037},
{"learn":[0.002470669271],"iteration":410,"passed_time":4.896683023,"remaining_time":7.017387593},
{"learn":[0.002470668057],"iteration":411,"passed_time":4.904837318,"remaining_time":7.000107629},
{"learn":[0.002470666707],"iteration":412,"passed_time":4.916645582,"remaining_time":6.988065271},
{"learn":[0.00247065908],"iteration":413,"passed_time":4.926185059,"remaining_time":6.972812668},
{"learn":[0.00247065773],"iteration":414,"passed_time":4.934260034,"remaining_time":6.955523181},
{"learn":[0.00247065638],"iteration":415,"passed_time":4.943050074,"remaining_time":6.939281834},
{"learn":[0.002470655031],"iteration":416,"passed_time":4.950884338,"remaining_time":6.921739974},
{"learn":[0.002470653681],"iteration":417,"passed_time":4.959214038,"remaining_time":6.904934378},
{"learn":[0.002470652332],"iteration":418,"passed_time":4.967266947,"remaining_time":6.887785432},
{"learn":[0.002470650983],"iteration":419,"passed_time":4.975706705,"remaining_time":6.871214021},
{"learn":[0.002470649634],"iteration":420,"passed_time":4.983487522,"remaining_time":6.853775001},
{"learn":[0.002470648285],"iteration":421,"passed_time":4.991857098,"remaining_time":6.837188158},
{"learn":[0.002470646936],"iteration":422,"passed_time":4.999735067,"remaining_time":6.819969583},
{"learn":[0.002470637261],"iteration":423,"passed_time":5.008288859,"remaining_time":6.803713167},
{"learn":[0.002470635912],"iteration":424,"passed_time":5.016148261,"remaining_time":6.78655353},
{"learn":[0.002470634563],"iteration":425,"passed_time":5.024529879,"remaining_time":6.770141198},
{"learn":[0.002470633215],"iteration":426,"passed_time":5.03237357,"remaining_time":6.753044627},
{"learn":[0.002470631866],"iteration":427,"passed_time":5.040649715,"remaining_time":6.736569246},
{"learn":[0.002470630517],"iteration":428,"passed_time":5.04853064,"remaining_time":6.719606051},
{"learn":[0.002470629169],"iteration":429,"passed_time":5.056974396,"remaining_time":6.703431176},
{"learn":[0.00247062782],"iteration":430,"passed_time":5.065146212,"remaining_time":6.686933167},
{"learn":[0.002470626472],"iteration":431,"passed_time":5.073110061,"remaining_time":6.670200266},
{"learn":[0.002470625124],"iteration":432,"passed_time":5.081083934,"remaining_time":6.653520994},
{"learn":[0.002470623776],"iteration":433,"passed_time":5.090386691,"remaining_time":6.638614901},
{"learn":[0.002470622427],"iteration":434,"passed_time":5.099524917,"remaining_time":6.623520869},
{"learn":[0.002470621079],"iteration":435,"passed_time":5.108749291,"remaining_time":6.608565596},
{"learn":[0.002470611036],"iteration":436,"passed_time":5.11820669,"remaining_time":6.593936765},
{"learn":[0.002470609688],"iteration":437,"passed_time":5.12618721,"remaining_time":6.577436557},
{"learn":[0.00247060834],"iteration":438,"passed_time":5.134846299,"remaining_time":6.561842309},
{"learn":[0.002470606992],"iteration":439,"passed_time":5.142960981,"remaining_time":6.545586703},
{"learn":[0.002470605645],"iteration":440,"passed_time":5.151312995,"remaining_time":6.529668854},
{"learn":[0.002470604297],"iteration":441,"passed_time":5.159565492,"remaining_time":6.513659603},
{"learn":[0.002470594286],"iteration":442,"passed_time":5.167930482,"remaining_time":6.497826814},
{"learn":[0.002470592938],"iteration":443,"passed_time":5.17613855,"remaining_time":6.481831158},
{"learn":[0.002470591591],"iteration":444,"passed_time":5.184111263,"remaining_time":6.465576969},
{"learn":[0.002470590244],"iteration":445,"passed_time":5.192395548,"remaining_time":6.449746936},
{"learn":[0.002470588897],"iteration":446,"passed_time":5.200377395,"remaining_time":6.433576509},
{"learn":[0.00247058755],"iteration":447,"passed_time":5.208943405,"remaining_time":6.41816241},
{"learn":[0.002470586203],"iteration":448,"passed_time":5.217008516,"remaining_time":6.402164126},
{"learn":[0.002470581203],"iteration":449,"passed_time":5.226303757,"remaining_time":6.387704592},
{"learn":[0.002470579856],"iteration":450,"passed_time":5.234358885,"remaining_time":6.371758377},
{"learn":[0.00247057851],"iteration":451,"passed_time":5.243827876,"remaining_time":6.35756123},
{"learn":[0.002470577163],"iteration":452,"passed_time":5.251920165,"remaining_time":6.341722583},
{"learn":[0.002470575816],"iteration":453,"passed_time":5.262735892,"remaining_time":6.329193386},
{"learn":[0.00247057447],"iteration":454,"passed_time":5.275319104,"remaining_time":6.318788817},
{"learn":[0.002470573123],"iteration":455,"passed_time":5.283930579,"remaining_time":6.30363648},
{"learn":[0.002470571777],"iteration":456,"passed_time":5.29347325,"remaining_time":6.289619201},
{"learn":[0.002470570431],"iteration":457,"passed_time":5.301764791,"remaining_time":6.274140866},
{"learn":[0.002470551155],"iteration":458,"passed_time":5.311020618,"remaining_time":6.259830401},
{"learn":[0.002470472495],"iteration":459,"passed_time":5.320926449,"remaining_time":6.246304961},
{"learn":[0.002470471149],"iteration":460,"passed_time":5.329049425,"remaining_time":6.230710716},
{"learn":[0.002470469804],"iteration":461,"passed_time":5.33879471,"remaining_time":6.217037996},
{"learn":[0.002470450602],"iteration":462,"passed_time":5.347241715,"remaining_time":6.201876459},
{"learn":[0.002470449257],"iteration":463,"passed_time":5.356589559,"remaining_time":6.187784491},
{"learn":[0.002470447911],"iteration":464,"passed_time":5.365930232,"remaining_time":6.173704675},
{"learn":[0.002470428726],"iteration":465,"passed_time":5.374417079,"remaining_time":6.158666781},
{"learn":[0.00247042633],"iteration":466,"passed_time":5.383823903,"remaining_time":6.144706938},
{"learn":[0.002470421363],"iteration":467,"passed_time":5.392252719,"remaining_time":6.1296548},
{"learn":[0.002470420017],"iteration":468,"passed_time":5.40164383,"remaining_time":6.115720413},
{"learn":[0.002470418672],"iteration":469,"passed_time":5.40986859,"remaining_time":6.100490112},
{"learn":[0.002470413707],"iteration":470,"passed_time":5.419550686,"remaining_time":6.086926355},
{"learn":[0.002470412362],"iteration":471,"passed_time":5.428198525,"remaining_time":6.072222079},
{"learn":[0.002470411017],"iteration":472,"passed_time":5.436723517,"remaining_time":6.05740654},
{"learn":[0.002470409672],"iteration":473,"passed_time":5.447907017,"remaining_time":6.045567702},
{"learn":[0.002470408327],"iteration":474,"passed_time":5.456741217,"remaining_time":6.03113503},
{"learn":[0.002470406982],"iteration":475,"passed_time":5.466307353,"remaining_time":6.017531623},
{"learn":[0.002470405637],"iteration":476,"passed_time":5.474684233,"remaining_time":6.002641203},
{"learn":[0.002470404293],"iteration":477,"passed_time":5.48370041,"remaining_time":5.98847618},
{"learn":[0.002470402948],"iteration":478,"passed_time":5.492977154,"remaining_time":5.974616069},
{"learn":[0.002470401604],"iteration":479,"passed_time":5.501093187,"remaining_time":5.959517619},
{"learn":[0.002470400259],"iteration":480,"passed_time":5.510532586,"remaining_time":5.945876116},
{"learn":[0.002470398915],"iteration":481,"passed_time":5.518833484,"remaining_time":5.931028516},
{"learn":[0.002470397571],"iteration":482,"passed_time":5.528227396,"remaining_time":5.917377978},
{"learn":[0.00247037841],"iteration":483,"passed_time":5.536399132,"remaining_time":5.90244205},
{"learn":[0.002470377066],"iteration":484,"passed_time":5.545651347,"remaining_time":5.888681327},
{"learn":[0.002470375722],"iteration":485,"passed_time":5.55439227,"remaining_time":5.874398409},
{"learn":[0.002470374378],"iteration":486,"passed_time":5.562899235,"remaining_time":5.859891802},
{"learn":[0.002470373034],"iteration":487,"passed_time":5.572272952,"remaining_time":5.846319162},
{"learn":[0.00247037169],"iteration":488,"passed_time":5.580243906,"remaining_time":5.831297824},
{"learn":[0.002470370347],"iteration":489,"passed_time":5.589853975,"remaining_time":5.81801128},
{"learn":[0.002470369003],"iteration":490,"passed_time":5.598035703,"remaining_time":5.803259008},
{"learn":[0.002470367659],"iteration":491,"passed_time":5.607244122,"remaining_time":5.789593524},
{"learn":[0.002470348515],"iteration":492,"passed_time":5.615951801,"remaining_time":5.775431162},
{"learn":[0.002470347171],"iteration":493,"passed_time":5.625958716,"remaining_time":5.762621681},
{"learn":[0.002470345828],"iteration":494,"passed_time":5.635897263,"remaining_time":5.749753774},
{"learn":[0.002470344484],"iteration":495,"passed_time":5.644989254,"remaining_time":5.736037468},
{"learn":[0.002470343141],"iteration":496,"passed_time":5.654352975,"remaining_time":5.722614782},
{"learn":[0.002470341798],"iteration":497,"passed_time":5.662468582,"remaining_time":5.707950258},
{"learn":[0.002470340455],"iteration":498,"passed_time":5.67129468,"remaining_time":5.69402532},
{"learn":[0.002470321326],"iteration":499,"passed_time":5.680545368,"remaining_time":5.680545368},
{"learn":[0.002470311768],"iteration":500,"passed_time":5.689303601,"remaining_time":5.66659181},
{"learn":[0.002470310425],"iteration":501,"passed_time":5.69877226,"remaining_time":5.653363716},
{"learn":[0.002470309082],"iteration":502,"passed_time":5.707158305,"remaining_time":5.63908087},
{"learn":[0.002470307739],"iteration":503,"passed_time":5.716544144,"remaining_time":5.625805348},
{"learn":[0.002470306396],"iteration":504,"passed_time":5.724647856,"remaining_time":5.611288492},
{"learn":[0.002470305053],"iteration":505,"passed_time":5.734146391,"remaining_time":5.598158729},
{"learn":[0.00247030371],"iteration":506,"passed_time":5.743419332,"remaining_time":5.584823927},
{"learn":[0.002470284606],"iteration":507,"passed_time":5.751993868,"remaining_time":5.570828707},
{"learn":[0.002470275061],"iteration":508,"passed_time":5.761560847,"remaining_time":5.557812133},
{"learn":[0.002470273719],"iteration":509,"passed_time":5.769734575,"remaining_time":5.543470474},
{"learn":[0.002470272376],"iteration":510,"passed_time":5.779099555,"remaining_time":5.53029292},
{"learn":[0.002470269905],"iteration":511,"passed_time":5.787473796,"remaining_time":5.516185962},
{"learn":[0.002470268562],"iteration":512,"passed_time":5.797856744,"remaining_time":5.504008254},
{"learn":[0.00247026722],"iteration":513,"passed_time":5.807731582,"remaining_time":5.491357099},
{"learn":[0.002470265877],"iteration":514,"passed_time":5.816534004,"remaining_time":5.477706781},
{"learn":[0.002470264535],"iteration":515,"passed_time":5.826041597,"remaining_time":5.464736691},
{"learn":[0.002470263192],"iteration":516,"passed_time":5.834170299,"remaining_time":5.450491788},
{"learn":[0.00247026185],"iteration":517,"passed_time":5.843474935,"remaining_time":5.437364708},
{"learn":[0.002470260508],"iteration":518,"passed_time":5.851943567,"remaining_time":5.423477564},
{"learn":[0.002470259166],"iteration":519,"passed_time":5.860410345,"remaining_time":5.409609549},
{"learn":[0.002470257824],"iteration":520,"passed_time":5.869690585,"remaining_time":5.396510154},
{"learn":[0.002470256482],"iteration":521,"passed_time":5.877778254,"remaining_time":5.382333344},
{"learn":[0.002470255141],"iteration":522,"passed_time":5.886920274,"remaining_time":5.369141435},
{"learn":[0.002470235372],"iteration":523,"passed_time":5.895346441,"remaining_time":5.355314706},
{"learn":[0.00247023403],"iteration":524,"passed_time":5.905419263,"remaining_time":5.34299838},
{"learn":[0.002470229091],"iteration":525,"passed_time":5.913898399,"remaining_time":5.329254451},
{"learn":[0.002470227749],"iteration":526,"passed_time":5.922798992,"remaining_time":5.315908773},
{"learn":[0.002470226408],"iteration":527,"passed_time":5.932291647,"remaining_time":5.303109199},
{"learn":[0.002470225067],"iteration":528,"passed_time":5.9419256,"remaining_time":5.290447935},
{"learn":[0.002470223726],"iteration":529,"passed_time":5.951497498,"remaining_time":5.277743065},
{"learn":[0.002470222385],"iteration":530,"passed_time":5.959585655,"remaining_time":5.263739495},
{"learn":[0.002470221044],"iteration":531,"passed_time":5.969145406,"remaining_time":5.251052726},
{"learn":[0.002470219703],"iteration":532,"passed_time":5.979799358,"remaining_time":5.239336399},
{"learn":[0.002470218362],"iteration":533,"passed_time":5.988832953,"remaining_time":5.22621003},
{"learn":[0.002470217021],"iteration":534,"passed_time":5.998607798,"remaining_time":5.213743226},
{"learn":[0.00247021568],"iteration":535,"passed_time":6.006724158,"remaining_time":5.199850763},
{"learn":[0.00247021434],"iteration":536,"passed_time":6.016189468,"remaining_time":5.187142874},
{"learn":[0.002470212999],"iteration":537,"passed_time":6.024243412,"remaining_time":5.173235049},
{"learn":[0.002470211659],"iteration":538,"passed_time":6.033132813,"remaining_time":5.1600635},
{"learn":[0.002470210318],"iteration":539,"passed_time":6.042093411,"remaining_time":5.146968461},
{"learn":[0.002470208978],"iteration":540,"passed_time":6.050177732,"remaining_time":5.133145247},
{"learn":[0.002470207638],"iteration":541,"passed_time":6.059628211,"remaining_time":5.12049764},
{"learn":[0.002470206298],"iteration":542,"passed_time":6.067641605,"remaining_time":5.106652327},
{"learn":[0.002470204958],"iteration":543,"passed_time":6.076295998,"remaining_time":5.093365763},
{"learn":[0.002470185222],"iteration":544,"passed_time":6.085066013,"remaining_time":5.080192726},
{"learn":[0.002470183882],"iteration":545,"passed_time":6.09439204,"remaining_time":5.067498144},
{"learn":[0.002470178954],"iteration":546,"passed_time":6.102575453,"remaining_time":5.053869616},
{"learn":[0.002470177614],"iteration":547,"passed_time":6.111378581,"remaining_time":5.040772114},
{"learn":[0.002470176275],"iteration":548,"passed_time":6.120635952,"remaining_time":5.028063414},
{"learn":[0.002470174935],"iteration":549,"passed_time":6.128751568,"remaining_time":5.014433101},
{"learn":[0.002470173596],"iteration":550,"passed_time":6.137920828,"remaining_time":5.001681401},
{"learn":[0.002470172256],"iteration":551,"passed_time":6.145847149,"remaining_time":4.987933918},
{"learn":[0.002470170917],"iteration":552,"passed_time":6.158159038,"remaining_time":4.977752423},
{"learn":[0.002470169578],"iteration":553,"passed_time":6.167078137,"remaining_time":4.964831857},
{"learn":[0.002470168239],"iteration":554,"passed_time":6.175573414,"remaining_time":4.95158589},
{"learn":[0.0024701669],"iteration":555,"passed_time":6.184922191,"remaining_time":4.939038584},
{"learn":[0.002470165561],"iteration":556,"passed_time":6.193177147,"remaining_time":4.925632812},
{"learn":[0.002470164222],"iteration":557,"passed_time":6.204333182,"remaining_time":4.914543488},
{"learn":[0.002470162883],"iteration":558,"passed_time":6.212588248,"remaining_time":4.901165326},
{"learn":[0.002470161545],"iteration":559,"passed_time":6.221575404,"remaining_time":4.888380674},
{"learn":[0.002470160206],"iteration":560,"passed_time":6.23084382,"remaining_time":4.875829656},
{"learn":[0.002470158868],"iteration":561,"passed_time":6.23885923,"remaining_time":4.862313777},
{"learn":[0.002470153938],"iteration":562,"passed_time":6.24824995,"remaining_time":4.849884952},
{"learn":[0.002470144088],"iteration":563,"passed_time":6.256630489,"remaining_time":4.836685981},
{"learn":[0.00247014275],"iteration":564,"passed_time":6.265917033,"remaining_time":4.824201609},
{"learn":[0.002470141412],"iteration":565,"passed_time":6.274033499,"remaining_time":4.81083134},
{"learn":[0.002470140074],"iteration":566,"passed_time":6.283579285,"remaining_time":4.798571129},
{"learn":[0.002470138736],"iteration":567,"passed_time":6.292214136,"remaining_time":4.785627653},
{"learn":[0.002470137398],"iteration":568,"passed_time":6.301106606,"remaining_time":4.772894459},
{"learn":[0.00247013606],"iteration":569,"passed_time":6.31038181,"remaining_time":4.760463471},
{"learn":[0.002470134722],"iteration":570,"passed_time":6.318398763,"remaining_time":4.747098195},
{"learn":[0.002470133384],"iteration":571,"passed_time":6.33039002,"remaining_time":4.7367254},
{"learn":[0.002470132047],"iteration":572,"passed_time":6.33852932,"remaining_time":4.723476474},
{"learn":[0.002470130709],"iteration":573,"passed_time":6.347592969,"remaining_time":4.710931368},
{"learn":[0.002470129371],"iteration":574,"passed_time":6.356853525,"remaining_time":4.69854391},
{"learn":[0.002470128034],"iteration":575,"passed_time":6.364808216,"remaining_time":4.685206048},
{"learn":[0.002470126697],"iteration":576,"passed_time":6.374053154,"remaining_time":4.672832728},
{"learn":[0.002470125359],"iteration":577,"passed_time":6.382196531,"remaining_time":4.659665979},
{"learn":[0.002470120435],"iteration":578,"passed_time":6.391799071,"remaining_time":4.647577563},
{"learn":[0.002470119098],"iteration":579,"passed_time":6.399868284,"remaining_time":4.634387378},
{"learn":[0.002470117761],"iteration":580,"passed_time":6.409209496,"remaining_time":4.62213215},
{"learn":[0.002470116424],"iteration":581,"passed_time":6.417317087,"remaining_time":4.609000932},
{"learn":[0.002470106906],"iteration":582,"passed_time":6.426432792,"remaining_time":4.596608017},
{"learn":[0.00247010557],"iteration":583,"passed_time":6.435590942,"remaining_time":4.584256561},
{"learn":[0.002470104233],"iteration":584,"passed_time":6.443746048,"remaining_time":4.571204461},
{"learn":[0.00247009472],"iteration":585,"passed_time":6.453395487,"remaining_time":4.559224798},
{"learn":[0.002470093383],"iteration":586,"passed_time":6.461721075,"remaining_time":4.546321642},
{"learn":[0.002470092046],"iteration":587,"passed_time":6.471863465,"remaining_time":4.534707054},
{"learn":[0.002470082537],"iteration":588,"passed_time":6.480337505,"remaining_time":4.521933301},
{"learn":[0.0024700812],"iteration":589,"passed_time":6.489274135,"remaining_time":4.509495585},
{"learn":[0.002470079864],"iteration":590,"passed_time":6.498435751,"remaining_time":4.497225418},
{"learn":[0.002470060197],"iteration":591,"passed_time":6.507989377,"remaining_time":4.485235922},
{"learn":[0.002470050699],"iteration":592,"passed_time":6.519480136,"remaining_time":4.474584174},
{"learn":[0.002470049362],"iteration":593,"passed_time":6.528051541,"remaining_time":4.461934218},
{"learn":[0.002470048026],"iteration":594,"passed_time":6.53668911,"remaining_time":4.449343008},
{"learn":[0.00247004669],"iteration":595,"passed_time":6.545619967,"remaining_time":4.436963871},
{"learn":[0.002470037196],"iteration":596,"passed_time":6.554127364,"remaining_time":4.424310432},
{"learn":[0.002470035859],"iteration":597,"passed_time":6.563590252,"remaining_time":4.41231318},
{"learn":[0.002470034523],"iteration":598,"passed_time":6.571830264,"remaining_time":4.399505736},
{"learn":[0.002470032069],"iteration":599,"passed_time":6.581613869,"remaining_time":4.387742579},
{"learn":[0.002470022579],"iteration":600,"passed_time":6.590074304,"remaining_time":4.375107566},
{"learn":[0.002470021243],"iteration":601,"passed_time":6.599160846,"remaining_time":4.36290036},
{"learn":[0.002470019908],"iteration":602,"passed_time":6.608170626,"remaining_time":4.350652966},
{"learn":[0.002470018572],"iteration":603,"passed_time":6.616178674,"remaining_time":4.337759528},
{"learn":[0.002470017236],"iteration":604,"passed_time":6.62569437,"remaining_time":4.325866572},
{"learn":[0.0024700159],"iteration":605,"passed_time":6.633809244,"remaining_time":4.313070696},
{"learn":[0.002470014565],"iteration":606,"passed_time":6.642988767,"remaining_time":4.300979548},
{"learn":[0.002470005079],"iteration":607,"passed_time":6.651396979,"remaining_time":4.288400684},
{"learn":[0.002470003744],"iteration":608,"passed_time":6.660866997,"remaining_time":4.276517234},
{"learn":[0.002470002408],"iteration":609,"passed_time":6.668798734,"remaining_time":4.263658207},
{"learn":[0.002470001073],"iteration":610,"passed_time":6.677623952,"remaining_time":4.251384152},
{"learn":[0.002469999738],"iteration":611,"passed_time":6.688569271,"remaining_time":4.240465485},
{"learn":[0.002469998402],"iteration":612,"passed_time":6.697708404,"remaining_time":4.228406447},
{"learn":[0.002469997067],"iteration":613,"passed_time":6.70708609,"remaining_time":4.21650689},
{"learn":[0.002469995732],"iteration":614,"passed_time":6.714955398,"remaining_time":4.203671265},
{"learn":[0.002469994397],"iteration":615,"passed_time":6.724108305,"remaining_time":4.19165193},
{"learn":[0.002469993062],"iteration":616,"passed_time":6.733050567,"remaining_time":4.17951113},
{"learn":[0.002469991728],"iteration":617,"passed_time":6.74133949,"remaining_time":4.166976837},
{"learn":[0.002469990393],"iteration":618,"passed_time":6.7517718,"remaining_time":4.155775534},
{"learn":[0.002469989058],"iteration":619,"passed_time":6.759770217,"remaining_time":4.143084972},
{"learn":[0.002469987724],"iteration":620,"passed_time":6.768917037,"remaining_time":4.131110398},
{"learn":[0.002469978242],"iteration":621,"passed_time":6.777565351,"remaining_time":4.118841966},
{"learn":[0.002469976907],"iteration":622,"passed_time":6.786663461,"remaining_time":4.106857343},
{"learn":[0.002469974538],"iteration":623,"passed_time":6.795527523,"remaining_time":4.094740944},
{"learn":[0.002469973203],"iteration":624,"passed_time":6.803778918,"remaining_time":4.082267351},
{"learn":[0.002469971869],"iteration":625,"passed_time":6.812752372,"remaining_time":4.070238637},
{"learn":[0.002469970534],"iteration":626,"passed_time":6.820665629,"remaining_time":4.057588963},
{"learn":[0.0024699692],"iteration":627,"passed_time":6.829383179,"remaining_time":4.0454308},
{"learn":[0.002469967866],"iteration":628,"passed_time":6.83727766,"remaining_time":4.032798111},
{"learn":[0.002469966532],"iteration":629,"passed_time":6.8454959,"remaining_time":4.020370608},
{"learn":[0.002469965198],"iteration":630,"passed_time":6.853334418,"remaining_time":4.00773439},
{"learn":[0.002469963864],"iteration":631,"passed_time":6.867435832,"remaining_time":3.998760105},
{"learn":[0.002469886673],"iteration":632,"passed_time":6.879439494,"remaining_time":3.988553387},
{"learn":[0.002469881792],"iteration":633,"passed_time":6.890015441,"remaining_time":3.9775168},
{"learn":[0.002469880459],"iteration":634,"passed_time":6.899359286,"remaining_time":3.965773448},
{"learn":[0.002469879126],"iteration":635,"passed_time":6.907995014,"remaining_time":3.953632367},
{"learn":[0.002469877793],"iteration":636,"passed_time":6.915822887,"remaining_time":3.941041928},
{"learn":[0.00246987646],"iteration":637,"passed_time":6.924205295,"remaining_time":3.928781061},
{"learn":[0.002469875128],"iteration":638,"passed_time":6.932083809,"remaining_time":3.91624766},
{"learn":[0.002469873795],"iteration":639,"passed_time":6.94026828,"remaining_time":3.903900908},
{"learn":[0.002469872462],"iteration":640,"passed_time":6.948183756,"remaining_time":3.891416487},
{"learn":[0.00246987113],"iteration":641,"passed_time":6.95651477,"remaining_time":3.879178018},
{"learn":[0.002469866405],"iteration":642,"passed_time":6.964613733,"remaining_time":3.866822866},
{"learn":[0.002469864043],"iteration":643,"passed_time":6.973560455,"remaining_time":3.854949568},
{"learn":[0.00246986271],"iteration":644,"passed_time":6.981455829,"remaining_time":3.842506696},
{"learn":[0.002469861378],"iteration":645,"passed_time":6.989769349,"remaining_time":3.830307043},
{"learn":[0.002469860046],"iteration":646,"passed_time":6.997788462,"remaining_time":3.817958774},
{"learn":[0.002469858713],"iteration":647,"passed_time":7.006279,"remaining_time":3.805879951},
{"learn":[0.002469857381],"iteration":648,"passed_time":7.014185988,"remaining_time":3.793496582},
{"learn":[0.002469856049],"iteration":649,"passed_time":7.02235797,"remaining_time":3.781269676},
{"learn":[0.002469854717],"iteration":650,"passed_time":7.030091566,"remaining_time":3.76882021},
{"learn":[0.002469852356],"iteration":651,"passed_time":7.040486626,"remaining_time":3.757805745},
{"learn":[0.002469851024],"iteration":652,"passed_time":7.049076777,"remaining_time":3.745834061},
{"learn":[0.002469849692],"iteration":653,"passed_time":7.058473666,"remaining_time":3.734299524},
{"learn":[0.00246984836],"iteration":654,"passed_time":7.067417541,"remaining_time":3.722532903},
{"learn":[0.002469847028],"iteration":655,"passed_time":7.075273411,"remaining_time":3.71020435},
{"learn":[0.002469845697],"iteration":656,"passed_time":7.083738691,"remaining_time":3.698207566},
{"learn":[0.002469844365],"iteration":657,"passed_time":7.091516668,"remaining_time":3.685864286},
{"learn":[0.002469839489],"iteration":658,"passed_time":7.101315852,"remaining_time":3.674580737},
{"learn":[0.002469838157],"iteration":659,"passed_time":7.109181719,"remaining_time":3.662305734},
{"learn":[0.002469836826],"iteration":660,"passed_time":7.118184464,"remaining_time":3.650627131},
{"learn":[0.002469835495],"iteration":661,"passed_time":7.126073977,"remaining_time":3.638388224},
{"learn":[0.002469830772],"iteration":662,"passed_time":7.140861571,"remaining_time":3.629668702},
{"learn":[0.002469825898],"iteration":663,"passed_time":7.150808357,"remaining_time":3.618481337},
{"learn":[0.002469821024],"iteration":664,"passed_time":7.160641525,"remaining_time":3.607240467},
{"learn":[0.002469819693],"iteration":665,"passed_time":7.169328796,"remaining_time":3.595429156},
{"learn":[0.002469818362],"iteration":666,"passed_time":7.178728061,"remaining_time":3.583982675},
{"learn":[0.002469817031],"iteration":667,"passed_time":7.186605934,"remaining_time":3.571786183},
{"learn":[0.002469815701],"iteration":668,"passed_time":7.196051505,"remaining_time":3.560378249},
{"learn":[0.00246981437],"iteration":669,"passed_time":7.204145528,"remaining_time":3.548310484},
{"learn":[0.002469813039],"iteration":670,"passed_time":7.215193357,"remaining_time":3.537702853},
{"learn":[0.002469811709],"iteration":671,"passed_time":7.225263846,"remaining_time":3.526616877},
{"learn":[0.002469810378],"iteration":672,"passed_time":7.233973205,"remaining_time":3.514872567},
{"learn":[0.002469808018],"iteration":673,"passed_time":7.243782237,"remaining_time":3.503669153},
{"learn":[0.002469806688],"iteration":674,"passed_time":7.252280678,"remaining_time":3.491838845},
{"learn":[0.002469805358],"iteration":675,"passed_time":7.260485466,"remaining_time":3.47987765},
{"learn":[0.002469804027],"iteration":676,"passed_time":7.269347815,"remaining_time":3.468241276},
{"learn":[0.002469802697],"iteration":677,"passed_time":7.277385089,"remaining_time":3.456221237},
{"learn":[0.002469801367],"iteration":678,"passed_time":7.286425609,"remaining_time":3.444687217},
{"learn":[0.002469800037],"iteration":679,"passed_time":7.294327607,"remaining_time":3.432624756},
{"learn":[0.002469798707],"iteration":680,"passed_time":7.303534288,"remaining_time":3.421185665},
{"learn":[0.002469797377],"iteration":681,"passed_time":7.311734731,"remaining_time":3.409283936},
{"learn":[0.002469796047],"iteration":682,"passed_time":7.320860363,"remaining_time":3.397822452},
{"learn":[0.002469794718],"iteration":683,"passed_time":7.33469325,"remaining_time":3.388542496},
{"learn":[0.002469793388],"iteration":684,"passed_time":7.342899804,"remaining_time":3.376661954},
{"learn":[0.002469788517],"iteration":685,"passed_time":7.353554633,"remaining_time":3.365912762},
{"learn":[0.002469787188],"iteration":686,"passed_time":7.362075703,"remaining_time":3.354191696},
{"learn":[0.002469785858],"iteration":687,"passed_time":7.371435412,"remaining_time":3.342860245},
{"learn":[0.002469784529],"iteration":688,"passed_time":7.380846944,"remaining_time":3.33155791},
{"learn":[0.0024697832],"iteration":689,"passed_time":7.390202227,"remaining_time":3.320235783},
{"learn":[0.00246978187],"iteration":690,"passed_time":7.403203969,"remaining_time":3.310549966},
{"learn":[0.002469780541],"iteration":691,"passed_time":7.41237068,"remaining_time":3.299147644},
{"learn":[0.002469779212],"iteration":692,"passed_time":7.420243873,"remaining_time":3.287178743},
{"learn":[0.002469777883],"iteration":693,"passed_time":7.430452817,"remaining_time":3.27625153},
{"learn":[0.002469776555],"iteration":694,"passed_time":7.444842988,"remaining_time":3.267161311},
{"learn":[0.002469775226],"iteration":695,"passed_time":7.453582267,"remaining_time":3.255587657},
{"learn":[0.002469773897],"iteration":696,"passed_time":7.462719026,"remaining_time":3.244194928},
{"learn":[0.002469772568],"iteration":697,"passed_time":7.471132368,"remaining_time":3.232495667},
{"learn":[0.00246977124],"iteration":698,"passed_time":7.485721953,"remaining_time":3.22346539},
{"learn":[0.002469766371],"iteration":699,"passed_time":7.495296974,"remaining_time":3.212270132},
{"learn":[0.002469761504],"iteration":700,"passed_time":7.503740895,"remaining_time":3.200597044},
{"learn":[0.002469760175],"iteration":701,"passed_time":7.517911157,"remaining_time":3.191363995},
{"learn":[0.002469758847],"iteration":702,"passed_time":7.527256518,"remaining_time":3.1800785},
{"learn":[0.002469757519],"iteration":703,"passed_time":7.535575272,"remaining_time":3.168366876},
{"learn":[0.002469752653],"iteration":704,"passed_time":7.546239476,"remaining_time":3.157646306},
{"learn":[0.002469747788],"iteration":705,"passed_time":7.55679503,"remaining_time":3.14688065},
{"learn":[0.00246974646],"iteration":706,"passed_time":7.567652155,"remaining_time":3.136240568},
{"learn":[0.002469745132],"iteration":707,"passed_time":7.576901438,"remaining_time":3.124936751},
{"learn":[0.002469743804],"iteration":708,"passed_time":7.590287879,"remaining_time":3.115336774},
{"learn":[0.002469742476],"iteration":709,"passed_time":7.599103895,"remaining_time":3.103859337},
{"learn":[0.002469737613],"iteration":710,"passed_time":7.608850882,"remaining_time":3.092767799},
{"learn":[0.002469736285],"iteration":711,"passed_time":7.621673504,"remaining_time":3.082924114},
{"learn":[0.002469734958],"iteration":712,"passed_time":7.632189359,"remaining_time":3.072143543},
{"learn":[0.00246973363],"iteration":713,"passed_time":7.641525868,"remaining_time":3.060891314},
{"learn":[0.002469732303],"iteration":714,"passed_time":7.651171108,"remaining_time":3.049767505},
{"learn":[0.002469730975],"iteration":715,"passed_time":7.659355379,"remaining_time":3.038068335},
{"learn":[0.002469726261],"iteration":716,"passed_time":7.669035219,"remaining_time":3.026969271},
{"learn":[0.0024697214],"iteration":717,"passed_time":7.679334207,"remaining_time":3.016117335},
{"learn":[0.002469720073],"iteration":718,"passed_time":7.687336553,"remaining_time":3.004369362},
{"learn":[0.00246971536],"iteration":719,"passed_time":7.697249286,"remaining_time":2.993374723},
{"learn":[0.002469714033],"iteration":720,"passed_time":7.705348887,"remaining_time":2.981681469},
{"learn":[0.002469712706],"iteration":721,"passed_time":7.714645558,"remaining_time":2.970459093},
{"learn":[0.002469707847],"iteration":722,"passed_time":7.723139925,"remaining_time":2.95893466},
{"learn":[0.00246970652],"iteration":723,"passed_time":7.732240039,"remaining_time":2.947649518},
{"learn":[0.002469705193],"iteration":724,"passed_time":7.742721309,"remaining_time":2.93689429},
{"learn":[0.002469703867],"iteration":725,"passed_time":7.752561392,"remaining_time":2.925897826},
{"learn":[0.00246970254],"iteration":726,"passed_time":7.761832389,"remaining_time":2.914690842},
{"learn":[0.002469701213],"iteration":727,"passed_time":7.769673654,"remaining_time":2.902954992},
{"learn":[0.002469699886],"iteration":728,"passed_time":7.778769019,"remaining_time":2.891696028},
{"learn":[0.00246969856],"iteration":729,"passed_time":7.786605485,"remaining_time":2.879977371},
{"learn":[0.002469697233],"iteration":730,"passed_time":7.795046591,"remaining_time":2.868491837},
{"learn":[0.002469695907],"iteration":731,"passed_time":7.803986959,"remaining_time":2.857197411},
{"learn":[0.002469694581],"iteration":732,"passed_time":7.81192372,"remaining_time":2.845543838},
{"learn":[0.002469693255],"iteration":733,"passed_time":7.820942661,"remaining_time":2.834292572},
{"learn":[0.002469690826],"iteration":734,"passed_time":7.830114633,"remaining_time":2.823102555},
{"learn":[0.0024696895],"iteration":735,"passed_time":7.839278371,"remaining_time":2.811915068},
{"learn":[0.002469688174],"iteration":736,"passed_time":7.847252207,"remaining_time":2.800308454},
{"learn":[0.002469686848],"iteration":737,"passed_time":7.856316287,"remaining_time":2.789098736},
{"learn":[0.002469682138],"iteration":738,"passed_time":7.864631156,"remaining_time":2.777630219},
{"learn":[0.002469680812],"iteration":739,"passed_time":7.87350995,"remaining_time":2.766368361},
{"learn":[0.002469679486],"iteration":740,"passed_time":7.882022435,"remaining_time":2.7549849},
{"learn":[0.002469677058],"iteration":741,"passed_time":7.890533227,"remaining_time":2.743608588},
{"learn":[0.002469675733],"iteration":742,"passed_time":7.899684325,"remaining_time":2.732461469},
{"learn":[0.002469674407],"iteration":743,"passed_time":7.907861906,"remaining_time":2.720984742},
{"learn":[0.00246967198],"iteration":744,"passed_time":7.917332452,"remaining_time":2.70995943},
{"learn":[0.002469667271],"iteration":745,"passed_time":7.926702669,"remaining_time":2.698904126},
{"learn":[0.002469664845],"iteration":746,"passed_time":7.938150058,"remaining_time":2.688556847},
{"learn":[0.002469663519],"iteration":747,"passed_time":7.947331541,"remaining_time":2.677443246},
{"learn":[0.002469662194],"iteration":748,"passed_time":7.955153162,"remaining_time":2.665879097},
{"learn":[0.002469660868],"iteration":749,"passed_time":7.964368596,"remaining_time":2.654789532},
{"learn":[0.002469659543],"iteration":750,"passed_time":7.972534709,"remaining_time":2.643357047},
{"learn":[0.002469658218],"iteration":751,"passed_time":7.981867234,"remaining_time":2.632317918},
{"learn":[0.002469656893],"iteration":752,"passed_time":7.989759413,"remaining_time":2.620810857},
{"learn":[0.002469655568],"iteration":753,"passed_time":7.999029118,"remaining_time":2.609762816},
{"learn":[0.00246961677],"iteration":754,"passed_time":8.007941692,"remaining_time":2.598603595},
{"learn":[0.002469615446],"iteration":755,"passed_time":8.016248439,"remaining_time":2.587254787},
{"learn":[0.002469614121],"iteration":756,"passed_time":8.025548747,"remaining_time":2.576232953},
{"learn":[0.002469612797],"iteration":757,"passed_time":8.033676763,"remaining_time":2.564841394},
{"learn":[0.002469611472],"iteration":758,"passed_time":8.04283695,"remaining_time":2.553786173},
{"learn":[0.002469572759],"iteration":759,"passed_time":8.051249053,"remaining_time":2.542499701},
{"learn":[0.002469534128],"iteration":760,"passed_time":8.061080517,"remaining_time":2.531666549},
{"learn":[0.002469532804],"iteration":761,"passed_time":8.069148188,"remaining_time":2.52028513},
{"learn":[0.002469531481],"iteration":762,"passed_time":8.079435518,"remaining_time":2.509601858},
{"learn":[0.002469530157],"iteration":763,"passed_time":8.088672503,"remaining_time":2.498595171},
{"learn":[0.002469528834],"iteration":764,"passed_time":8.097726542,"remaining_time":2.487536912},
{"learn":[0.00246952751],"iteration":765,"passed_time":8.108524208,"remaining_time":2.477016534},
{"learn":[0.002469526187],"iteration":766,"passed_time":8.116429631,"remaining_time":2.465616824},
{"learn":[0.002469524864],"iteration":767,"passed_time":8.125721601,"remaining_time":2.454645067},
{"learn":[0.002469523541],"iteration":768,"passed_time":8.134599279,"remaining_time":2.44355323},
{"learn":[0.002469504263],"iteration":769,"passed_time":8.14302153,"remaining_time":2.432331107},
{"learn":[0.00246950294],"iteration":770,"passed_time":8.152193452,"remaining_time":2.421338911},
{"learn":[0.002469501617],"iteration":771,"passed_time":8.160130265,"remaining_time":2.409986659},
{"learn":[0.002469500294],"iteration":772,"passed_time":8.169227992,"remaining_time":2.398984158},
{"learn":[0.002469498972],"iteration":773,"passed_time":8.177083744,"remaining_time":2.387623936},
{"learn":[0.002469497649],"iteration":774,"passed_time":8.186439517,"remaining_time":2.376708247},
{"learn":[0.002469496327],"iteration":775,"passed_time":8.194404511,"remaining_time":2.365395117},
{"learn":[0.002469495004],"iteration":776,"passed_time":8.203482218,"remaining_time":2.354409955},
{"learn":[0.002469493682],"iteration":777,"passed_time":8.211899208,"remaining_time":2.343241162},
{"learn":[0.00246949236],"iteration":778,"passed_time":8.22004734,"remaining_time":2.332003161},
{"learn":[0.002469473104],"iteration":779,"passed_time":8.229642908,"remaining_time":2.321181333},
{"learn":[0.002469471782],"iteration":780,"passed_time":8.237564674,"remaining_time":2.309893295},
{"learn":[0.00246947046],"iteration":781,"passed_time":8.246443544,"remaining_time":2.298880681},
{"learn":[0.002469469138],"iteration":782,"passed_time":8.254540918,"remaining_time":2.287656934},
{"learn":[0.002469467816],"iteration":783,"passed_time":8.263624641,"remaining_time":2.276712911},
{"learn":[0.002469466495],"iteration":784,"passed_time":8.272777219,"remaining_time":2.265792487},
{"learn":[0.002469465173],"iteration":785,"passed_time":8.283817396,"remaining_time":2.255390487},
{"learn":[0.002469463852],"iteration":786,"passed_time":8.293163305,"remaining_time":2.244528315},
{"learn":[0.00246946253],"iteration":787,"passed_time":8.30120252,"remaining_time":2.233318444},
{"learn":[0.002469461209],"iteration":788,"passed_time":8.310707305,"remaining_time":2.222508544},
{"learn":[0.002469459887],"iteration":789,"passed_time":8.318828714,"remaining_time":2.211334215},
{"learn":[0.002469458566],"iteration":790,"passed_time":8.327982548,"remaining_time":2.200440395},
{"learn":[0.002469457245],"iteration":791,"passed_time":8.336074668,"remaining_time":2.189272135},
{"learn":[0.002469455924],"iteration":792,"passed_time":8.345391023,"remaining_time":2.1784312},
{"learn":[0.002469454603],"iteration":793,"passed_time":8.355847267,"remaining_time":2.167889845},
{"learn":[0.002469452263],"iteration":794,"passed_time":8.364250448,"remaining_time":2.156819298},
{"learn":[0.002469450942],"iteration":795,"passed_time":8.373435045,"remaining_time":2.145955715},
{"learn":[0.002469449621],"iteration":796,"passed_time":8.381315309,"remaining_time":2.134764125},
{"learn":[0.0024694483],"iteration":797,"passed_time":8.390580823,"remaining_time":2.123931486},
{"learn":[0.00246944698],"iteration":798,"passed_time":8.398670637,"remaining_time":2.112807006},
{"learn":[0.002469445659],"iteration":799,"passed_time":8.407616528,"remaining_time":2.101904132},
{"learn":[0.002469426428],"iteration":800,"passed_time":8.416889616,"remaining_time":2.091087433},
{"learn":[0.00246942409],"iteration":801,"passed_time":8.425248603,"remaining_time":2.080048907},
{"learn":[0.00246942277],"iteration":802,"passed_time":8.43437405,"remaining_time":2.069205091},
{"learn":[0.002469421449],"iteration":803,"passed_time":8.442360784,"remaining_time":2.058087952},
{"learn":[0.002469402241],"iteration":804,"passed_time":8.45331664,"remaining_time":2.04769782},
{"learn":[0.002469400921],"iteration":805,"passed_time":8.461492053,"remaining_time":2.036637045},
{"learn":[0.002469399601],"iteration":806,"passed_time":8.472199966,"remaining_time":2.026189087},
{"learn":[0.002469398281],"iteration":807,"passed_time":8.481589811,"remaining_time":2.015427282},
{"learn":[0.002469396961],"iteration":808,"passed_time":8.489538039,"remaining_time":2.004328511},
{"learn":[0.002469395642],"iteration":809,"passed_time":8.498959665,"remaining_time":1.993583131},
{"learn":[0.002469394322],"iteration":810,"passed_time":8.506950154,"remaining_time":1.982507496},
{"learn":[0.002469393003],"iteration":811,"passed_time":8.515992387,"remaining_time":1.971682967},
{"learn":[0.002469391683],"iteration":812,"passed_time":8.523860653,"remaining_time":1.960592795},
{"learn":[0.002469390364],"iteration":813,"passed_time":8.533048641,"remaining_time":1.949812097},
{"learn":[0.002469371178],"iteration":814,"passed_time":8.541865312,"remaining_time":1.938951022},
{"learn":[0.002469369858],"iteration":815,"passed_time":8.550199669,"remaining_time":1.9279862},
{"learn":[0.002469368539],"iteration":816,"passed_time":8.559354215,"remaining_time":1.917211532},
{"learn":[0.00246936722],"iteration":817,"passed_time":8.567528427,"remaining_time":1.906222706},
{"learn":[0.002469364885],"iteration":818,"passed_time":8.577224034,"remaining_time":1.895576984},
{"learn":[0.002469363566],"iteration":819,"passed_time":8.585094584,"remaining_time":1.884532957},
{"learn":[0.002469362248],"iteration":820,"passed_time":8.594261435,"remaining_time":1.87377929},
{"learn":[0.002469360929],"iteration":821,"passed_time":8.602133912,"remaining_time":1.862749193},
{"learn":[0.002469341766],"iteration":822,"passed_time":8.611973675,"remaining_time":1.852149867},
{"learn":[0.002469340447],"iteration":823,"passed_time":8.620195094,"remaining_time":1.841206719},
{"learn":[0.002469339129],"iteration":824,"passed_time":8.629745787,"remaining_time":1.830552137},
{"learn":[0.00246933781],"iteration":825,"passed_time":8.639503685,"remaining_time":1.819943876},
{"learn":[0.002469336492],"iteration":826,"passed_time":8.64812866,"remaining_time":1.809100675},
{"learn":[0.002469335174],"iteration":827,"passed_time":8.657340782,"remaining_time":1.7983848},
{"learn":[0.002469333856],"iteration":828,"passed_time":8.665253046,"remaining_time":1.787404428},
{"learn":[0.002469332538],"iteration":829,"passed_time":8.674657754,"remaining_time":1.77673713},
{"learn":[0.00246933122],"iteration":830,"passed_time":8.682844721,"remaining_time":1.76582522},
{"learn":[0.002469329902],"iteration":831,"passed_time":8.690681835,"remaining_time":1.754849217},
{"learn":[0.002469328584],"iteration":832,"passed_time":8.699110946,"remaining_time":1.743999433},
{"learn":[0.002469327266],"iteration":833,"passed_time":8.707083258,"remaining_time":1.733064533},
{"learn":[0.002469324933],"iteration":834,"passed_time":8.716048374,"remaining_time":1.722332912},
{"learn":[0.002469317043],"iteration":835,"passed_time":8.724640571,"remaining_time":1.711532361},
{"learn":[0.00246931471],"iteration":836,"passed_time":8.733457855,"remaining_time":1.70078092},
{"learn":[0.00246931471],"iteration":837,"passed_time":8.741272675,"remaining_time":1.689840302},
{"learn":[0.00246931471],"iteration":838,"passed_time":8.749552193,"remaining_time":1.678996309},
{"learn":[0.00246931471],"iteration":839,"passed_time":8.757500922,"remaining_time":1.668095414},
{"learn":[0.00246931471],"iteration":840,"passed_time":8.766104918,"remaining_time":1.657325424},
{"learn":[0.00246931471],"iteration":841,"passed_time":8.774089443,"remaining_time":1.646444337},
{"learn":[0.002469312378],"iteration":842,"passed_time":8.783003699,"remaining_time":1.635743275},
{"learn":[0.002469310045],"iteration":843,"passed_time":8.791513866,"remaining_time":1.624971757},
{"learn":[0.002469310045],"iteration":844,"passed_time":8.799823835,"remaining_time":1.614168869},
{"learn":[0.002469310045],"iteration":845,"passed_time":8.809594492,"remaining_time":1.603637768},
{"learn":[0.002469290911],"iteration":846,"passed_time":8.819278397,"remaining_time":1.593092792},
{"learn":[0.002469290911],"iteration":847,"passed_time":8.828570224,"remaining_time":1.582479568},
{"learn":[0.00246928858],"iteration":848,"passed_time":8.836829697,"remaining_time":1.571685847},
{"learn":[0.00246928858],"iteration":849,"passed_time":8.845463274,"remaining_time":1.560964107},
{"learn":[0.00246928858],"iteration":850,"passed_time":8.853260035,"remaining_time":1.550100758},
{"learn":[0.002469214915],"iteration":851,"passed_time":8.862162552,"remaining_time":1.539436687},
{"learn":[0.002469214915],"iteration":852,"passed_time":8.870129506,"remaining_time":1.528615519},
{"learn":[0.002469214915],"iteration":853,"passed_time":8.878440227,"remaining_time":1.517859805},
{"learn":[0.002469214915],"iteration":854,"passed_time":8.886193067,"remaining_time":1.507015198},
{"learn":[0.002469214915],"iteration":855,"passed_time":8.894355626,"remaining_time":1.496246741},
{"learn":[0.002469214915],"iteration":856,"passed_time":8.902504617,"remaining_time":1.485482101},
{"learn":[0.002469214915],"iteration":857,"passed_time":8.91047382,"remaining_time":1.474693802},
{"learn":[0.002469214915],"iteration":858,"passed_time":8.918247444,"remaining_time":1.463879965},
{"learn":[0.002469214915],"iteration":859,"passed_time":8.926061403,"remaining_time":1.453079763},
{"learn":[0.002469214915],"iteration":860,"passed_time":8.934029285,"remaining_time":1.442311348},
{"learn":[0.002469214915],"iteration":861,"passed_time":8.941979364,"remaining_time":1.43154658},
{"learn":[0.002469214915],"iteration":862,"passed_time":8.950082772,"remaining_time":1.420812677},
{"learn":[0.002469214915],"iteration":863,"passed_time":8.957829954,"remaining_time":1.410028789},
{"learn":[0.002469214915],"iteration":864,"passed_time":8.966338636,"remaining_time":1.39937077},
{"learn":[0.002469214915],"iteration":865,"passed_time":8.974141133,"remaining_time":1.388608443},
{"learn":[0.002469214915],"iteration":866,"passed_time":8.984872922,"remaining_time":1.378302305},
{"learn":[0.002469214915],"iteration":867,"passed_time":8.992722516,"remaining_time":1.36755688},
{"learn":[0.002469195855],"iteration":868,"passed_time":9.002553838,"remaining_time":1.357116862},
{"learn":[0.002469195855],"iteration":869,"passed_time":9.010443453,"remaining_time":1.346388102},
{"learn":[0.002469195855],"iteration":870,"passed_time":9.020873451,"remaining_time":1.336042107},
{"learn":[0.002469195855],"iteration":871,"passed_time":9.030070674,"remaining_time":1.325514961},
{"learn":[0.002469195855],"iteration":872,"passed_time":9.03795675,"remaining_time":1.314800123},
{"learn":[0.002469195855],"iteration":873,"passed_time":9.047096839,"remaining_time":1.304272542},
{"learn":[0.002469195855],"iteration":874,"passed_time":9.05518166,"remaining_time":1.29359738},
{"learn":[0.002469195855],"iteration":875,"passed_time":9.064966981,"remaining_time":1.283168842},
{"learn":[0.002469195855],"iteration":876,"passed_time":9.073008285,"remaining_time":1.272497171},
{"learn":[0.002469195855],"iteration":877,"passed_time":9.082137805,"remaining_time":1.261982702},
{"learn":[0.002469195855],"iteration":878,"passed_time":9.09007881,"remaining_time":1.251307777},
{"learn":[0.002469195855],"iteration":879,"passed_time":9.099085022,"remaining_time":1.240784321},
{"learn":[0.002469195855],"iteration":880,"passed_time":9.107701755,"remaining_time":1.230211701},
{"learn":[0.002469195855],"iteration":881,"passed_time":9.115876214,"remaining_time":1.219584346},
{"learn":[0.002469195855],"iteration":882,"passed_time":9.125214643,"remaining_time":1.209116776},
{"learn":[0.002469195855],"iteration":883,"passed_time":9.133018834,"remaining_time":1.198450435},
{"learn":[0.002469195855],"iteration":884,"passed_time":9.142269876,"remaining_time":1.187978571},
{"learn":[0.002469195855],"iteration":885,"passed_time":9.150078837,"remaining_time":1.177323914},
{"learn":[0.002469195855],"iteration":886,"passed_time":9.165978346,"remaining_time":1.167706373},
{"learn":[0.002469176815],"iteration":887,"passed_time":9.175765393,"remaining_time":1.157303743},
{"learn":[0.002469176815],"iteration":888,"passed_time":9.183696813,"remaining_time":1.146670806},
{"learn":[0.002469176815],"iteration":889,"passed_time":9.19283109,"remaining_time":1.136192607},
{"learn":[0.002469176815],"iteration":890,"passed_time":9.200770592,"remaining_time":1.125571262},
{"learn":[0.002469176815],"iteration":891,"passed_time":9.209222983,"remaining_time":1.115018029},
{"learn":[0.002469176815],"iteration":892,"passed_time":9.218096475,"remaining_time":1.104519958},
{"learn":[0.002469176815],"iteration":893,"passed_time":9.226468974,"remaining_time":1.09396612},
{"learn":[0.002469176815],"iteration":894,"passed_time":9.235605623,"remaining_time":1.083506805},
{"learn":[0.002469176815],"iteration":895,"passed_time":9.243685529,"remaining_time":1.072927785},
{"learn":[0.002469176815],"iteration":896,"passed_time":9.252825715,"remaining_time":1.062476085},
{"learn":[0.002469176815],"iteration":897,"passed_time":9.26073478,"remaining_time":1.051887469},
{"learn":[0.002469176815],"iteration":898,"passed_time":9.269890181,"remaining_time":1.041444837},
{"learn":[0.002469157795],"iteration":899,"passed_time":9.27832267,"remaining_time":1.030924741},
{"learn":[0.002469157795],"iteration":900,"passed_time":9.287788932,"remaining_time":1.020522868},
{"learn":[0.002469157795],"iteration":901,"passed_time":9.296822063,"remaining_time":1.010076011},
{"learn":[0.002469157795],"iteration":902,"passed_time":9.304775823,"remaining_time":0.9995163398},
{"learn":[0.002469157795],"iteration":903,"passed_time":9.313991461,"remaining_time":0.9890964383},
{"learn":[0.002469157795],"iteration":904,"passed_time":9.32221114,"remaining_time":0.97857465},
{"learn":[0.002469157795],"iteration":905,"passed_time":9.331317127,"remaining_time":0.9681499006},
{"learn":[0.002469157795],"iteration":906,"passed_time":9.34023482,"remaining_time":0.9577087522},
{"learn":[0.002469157795],"iteration":907,"passed_time":9.35067319,"remaining_time":0.9474250369},
{"learn":[0.002469157795],"iteration":908,"passed_time":9.359653437,"remaining_time":0.9369950085},
{"learn":[0.002469157795],"iteration":909,"passed_time":9.367692804,"remaining_time":0.9264751125},
{"learn":[0.002469138795],"iteration":910,"passed_time":9.377967291,"remaining_time":0.9161790218},
{"learn":[0.002469138795],"iteration":911,"passed_time":9.386082569,"remaining_time":0.9056746339},
{"learn":[0.002469138795],"iteration":912,"passed_time":9.395223589,"remaining_time":0.8952732226},
{"learn":[0.002469138795],"iteration":913,"passed_time":9.40302919,"remaining_time":0.8847489172},
{"learn":[0.002469138795],"iteration":914,"passed_time":9.412425393,"remaining_time":0.8743783152},
{"learn":[0.002469138795],"iteration":915,"passed_time":9.438684319,"remaining_time":0.8655562039},
{"learn":[0.002469138795],"iteration":916,"passed_time":9.456434879,"remaining_time":0.8559259487},
{"learn":[0.002469138795],"iteration":917,"passed_time":9.468238513,"remaining_time":0.8457467953},
{"learn":[0.002469138795],"iteration":918,"passed_time":9.479747342,"remaining_time":0.8355381226},
{"learn":[0.002469138795],"iteration":919,"passed_time":9.490118691,"remaining_time":0.8252277122},
{"learn":[0.002469138795],"iteration":920,"passed_time":9.500912928,"remaining_time":0.8149534434},
{"learn":[0.002469138795],"iteration":921,"passed_time":9.511383167,"remaining_time":0.8046506367},
{"learn":[0.002469138795],"iteration":922,"passed_time":9.519572026,"remaining_time":0.7941571463},
{"learn":[0.002469138795],"iteration":923,"passed_time":9.528750362,"remaining_time":0.7837500298},
{"learn":[0.002469138795],"iteration":924,"passed_time":9.537004072,"remaining_time":0.7732706005},
{"learn":[0.002469138795],"iteration":925,"passed_time":9.54567561,"remaining_time":0.7628293684},
{"learn":[0.002469138795],"iteration":926,"passed_time":9.55374357,"remaining_time":0.7523444235},
{"learn":[0.002469138795],"iteration":927,"passed_time":9.562106086,"remaining_time":0.7418875412},
{"learn":[0.002469138795],"iteration":928,"passed_time":9.571085234,"remaining_time":0.7314822945},
{"learn":[0.002469138795],"iteration":929,"passed_time":9.578949155,"remaining_time":0.7209961729},
{"learn":[0.002469138795],"iteration":930,"passed_time":9.588153172,"remaining_time":0.7106150042},
{"learn":[0.002469138795],"iteration":931,"passed_time":9.596010464,"remaining_time":0.7001381025},
{"learn":[0.002469138795],"iteration":932,"passed_time":9.607997298,"remaining_time":0.6899633644},
{"learn":[0.002469119815],"iteration":933,"passed_time":9.616943985,"remaining_time":0.6795699176},
{"learn":[0.002469119815],"iteration":934,"passed_time":9.62538995,"remaining_time":0.6691447559},
{"learn":[0.002469119815],"iteration":935,"passed_time":9.634654829,"remaining_time":0.6587798174},
{"learn":[0.002469119815],"iteration":936,"passed_time":9.642535883,"remaining_time":0.6483241842},
{"learn":[0.002469119815],"iteration":937,"passed_time":9.651718023,"remaining_time":0.6379600399},
{"learn":[0.002469119815],"iteration":938,"passed_time":9.659582441,"remaining_time":0.6275128103},
{"learn":[0.002469119815],"iteration":939,"passed_time":9.668665629,"remaining_time":0.6171488699},
{"learn":[0.002469119815],"iteration":940,"passed_time":9.676574244,"remaining_time":0.6067140068},
{"learn":[0.002469119815],"iteration":941,"passed_time":9.685952929,"remaining_time":0.5963750211},
{"learn":[0.002469119815],"iteration":942,"passed_time":9.693891281,"remaining_time":0.5859510106},
{"learn":[0.002469119815],"iteration":943,"passed_time":9.702748723,"remaining_time":0.5755867886},
{"learn":[0.002469119815],"iteration":944,"passed_time":9.710911865,"remaining_time":0.5651853466},
{"learn":[0.002469119815],"iteration":945,"passed_time":9.719329975,"remaining_time":0.5548031909},
{"learn":[0.002469119815],"iteration":946,"passed_time":9.728354458,"remaining_time":0.5444591196},
{"learn":[0.002469119815],"iteration":947,"passed_time":9.736317514,"remaining_time":0.5340596105},
{"learn":[0.002469119815],"iteration":948,"passed_time":9.745517461,"remaining_time":0.5237317076},
{"learn":[0.002469119815],"iteration":949,"passed_time":9.753345796,"remaining_time":0.5133339893},
{"learn":[0.002469119815],"iteration":950,"passed_time":9.762642527,"remaining_time":0.5030173332},
{"learn":[0.002469119815],"iteration":951,"passed_time":9.77053015,"remaining_time":0.4926317722},
{"learn":[0.002469100856],"iteration":952,"passed_time":9.781413585,"remaining_time":0.4823992009},
{"learn":[0.002469100856],"iteration":953,"passed_time":9.78956502,"remaining_time":0.4720335335},
{"learn":[0.002469100856],"iteration":954,"passed_time":9.799704647,"remaining_time":0.4617661876},
{"learn":[0.002469100856],"iteration":955,"passed_time":9.808647398,"remaining_time":0.4514440225},
{"learn":[0.002469091605],"iteration":956,"passed_time":9.817130843,"remaining_time":0.4411041027},
{"learn":[0.002469091605],"iteration":957,"passed_time":9.826192028,"remaining_time":0.4307933874},
{"learn":[0.002469091605],"iteration":958,"passed_time":9.834044536,"remaining_time":0.4204336037},
{"learn":[0.002469082358],"iteration":959,"passed_time":9.843669552,"remaining_time":0.410152898},
{"learn":[0.002469082358],"iteration":960,"passed_time":9.851594641,"remaining_time":0.3998045692},
{"learn":[0.002469082358],"iteration":961,"passed_time":9.860396313,"remaining_time":0.3894959043},
{"learn":[0.002469082358],"iteration":962,"passed_time":9.868838154,"remaining_time":0.3791765438},
{"learn":[0.002469082358],"iteration":963,"passed_time":9.878050528,"remaining_time":0.3688898537},
{"learn":[0.002469073115],"iteration":964,"passed_time":9.887670621,"remaining_time":0.358620178},
{"learn":[0.002469073115],"iteration":965,"passed_time":9.895509754,"remaining_time":0.3482891632},
{"learn":[0.002469073115],"iteration":966,"passed_time":9.904588509,"remaining_time":0.3380056058},
{"learn":[0.002469073115],"iteration":967,"passed_time":9.912625355,"remaining_time":0.3276900944},
{"learn":[0.002469073115],"iteration":968,"passed_time":9.922050697,"remaining_time":0.3174237065},
{"learn":[0.002469063876],"iteration":969,"passed_time":9.930370425,"remaining_time":0.3071248585},
{"learn":[0.002469063876],"iteration":970,"passed_time":9.939086485,"remaining_time":0.2968419239},
{"learn":[0.002469063876],"iteration":971,"passed_time":9.947559515,"remaining_time":0.2865552124},
{"learn":[0.002469063876],"iteration":972,"passed_time":9.957291154,"remaining_time":0.2763071543},
{"learn":[0.002469063876],"iteration":973,"passed_time":9.967356717,"remaining_time":0.2660690705},
{"learn":[0.002469063876],"iteration":974,"passed_time":9.975788675,"remaining_time":0.2557894532},
{"learn":[0.002469063876],"iteration":975,"passed_time":9.985033705,"remaining_time":0.2455336157},
{"learn":[0.002469063876],"iteration":976,"passed_time":9.993031717,"remaining_time":0.2352504908},
{"learn":[0.002469063876],"iteration":977,"passed_time":10.00176049,"remaining_time":0.2249884774},
{"learn":[0.002469063876],"iteration":978,"passed_time":10.01058938,"remaining_time":0.2147317437},
{"learn":[0.002469063876],"iteration":979,"passed_time":10.01854736,"remaining_time":0.2044601503},
{"learn":[0.002469044962],"iteration":980,"passed_time":10.02832882,"remaining_time":0.1942285908},
{"learn":[0.002469044962],"iteration":981,"passed_time":10.03620649,"remaining_time":0.1839630517},
{"learn":[0.002469044962],"iteration":982,"passed_time":10.04530911,"remaining_time":0.1737235554},
{"learn":[0.002469044962],"iteration":983,"passed_time":10.05325764,"remaining_time":0.1634676039},
{"learn":[0.002469044962],"iteration":984,"passed_time":10.06228576,"remaining_time":0.153232778},
{"learn":[0.002469044962],"iteration":985,"passed_time":10.07010283,"remaining_time":0.1429832044},
{"learn":[0.002469044962],"iteration":986,"passed_time":10.07939032,"remaining_time":0.1327579272},
{"learn":[0.002469044962],"iteration":987,"passed_time":10.08736756,"remaining_time":0.1225186343},
{"learn":[0.002469044962],"iteration":988,"passed_time":10.09616095,"remaining_time":0.1122929934},
{"learn":[0.002469044962],"iteration":989,"passed_time":10.10505639,"remaining_time":0.1020712767},
{"learn":[0.002469035734],"iteration":990,"passed_time":10.11362785,"remaining_time":0.09184929431},
{"learn":[0.002469035734],"iteration":991,"passed_time":10.12288068,"remaining_time":0.08163613453},
{"learn":[0.002469035734],"iteration":992,"passed_time":10.13196127,"remaining_time":0.07142369475},
{"learn":[0.002469026509],"iteration":993,"passed_time":10.14420636,"remaining_time":0.06123263396},
{"learn":[0.002469026509],"iteration":994,"passed_time":10.15285098,"remaining_time":0.05101935164},
{"learn":[0.002469026509],"iteration":995,"passed_time":10.16098003,"remaining_time":0.04080714871},
{"learn":[0.002469026509],"iteration":996,"passed_time":10.1700985,"remaining_time":0.0306021018},
{"learn":[0.002469026509],"iteration":997,"passed_time":10.17788867,"remaining_time":0.02039657048},
{"learn":[0.002469026509],"iteration":998,"passed_time":10.18714447,"remaining_time":0.01019734181},
{"learn":[0.002469026509],"iteration":999,"passed_time":10.19500935,"remaining_time":0}
]}